Workbook
Name DAM: #REF!
Name DAM: #REF!
Name DAM: #REF!
Name DAM: 'Rechenblatt Koper neu'!$B$4
Name DAM: 'Rechenblatt neu'!$B$4
Name DAM: #REF!
Name DAM: #REF!
Name DAM: #REF!
Name DAMHQ: #REF!
Name DAMHQ: #REF!
Name DAMHQ: #REF!
Name DAMHQ: 'Rechenblatt Koper neu'!$E$4
Name DAMHQ: 'Rechenblatt neu'!$E$4
Name DAMHQ: #REF!
Name DAMHQ: #REF!
Name DAMHQ: #REF!
Name FEBP: #REF!
Name FEBP: #REF!
Name FEBP: #REF!
Name FEBP: 'Rechenblatt Koper neu'!$B$3
Name FEBP: 'Rechenblatt neu'!$B$3
Name FEBP: #REF!
Name FEBP: #REF!
Name FEBP: #REF!
Name FEBP20: #REF!
Name FEBP20: #REF!
Name FEBP20: #REF!
Name FEBP20: 'Rechenblatt Koper neu'!$C$3
Name FEBP20: 'Rechenblatt neu'!$C$3
Name FEBP20: #REF!
Name FEBP20: #REF!
Name FEBP20: #REF!
Name FEBP40: #REF!
Name FEBP40: #REF!
Name FEBP40: #REF!
Name FEBP40: 'Rechenblatt Koper neu'!$D$3
Name FEBP40: 'Rechenblatt neu'!$D$3
Name FEBP40: #REF!
Name FEBP40: #REF!
Name FEBP40: #REF!
Name FEBPHQ: #REF!
Name FEBPHQ: #REF!
Name FEBPHQ: #REF!
Name FEBPHQ: 'Rechenblatt Koper neu'!$E$3
Name FEBPHQ: 'Rechenblatt neu'!$E$3
Name FEBPHQ: #REF!
Name FEBPHQ: #REF!
Name FEBPHQ: #REF!
Name HCM: #REF!
Name HCM: #REF!
Name HCM: #REF!
Name HCM: 'Rechenblatt Koper neu'!$B$7
Name HCM: 'Rechenblatt neu'!$B$7
Name HCM: #REF!
Name HCM: #REF!
Name HCM: #REF!
Name JEA: #REF!
Name JEA: #REF!
Name JEA: #REF!
Name JEA: 'Rechenblatt Koper neu'!$B$6

Sheet Introduction
B7: Europe - Far East Ratesheet
D8: NEW: rate reference mentioned in your email
B9: valid as from 01.12.2025 - 31.01.2026
B10: Special Equipment: FE140000
B11: valid as from 01.01.2026 - 31.01.2026
B12: Reefer: RFT21181
B13: =B9 -> valid as from 01.12.2025 - 31.01.2026
B17: Your rate document is confidential – the contents shall not be disclosed to competitors of OOCL
B19: For forwarders located in Germany, Austria, Czech and Slovakia only
B20: Commodity Cargo all Kinds FAK
B22: Please provide the exact commodity description already at time of booking (no brand/product names).
B23: HS codes would be appreciated
B25: DAY 9 Product
B26: Loops
B27: LL1 | C27: LL2 | D27: LL3 | E27: LL4 | F27: LL5 | G27: LL6 | H27: LL7
B28: ZEE | C28: HAM | D28: RTM | E28: DKK | F28: ANR | G28: HAM | H28: ANR
B29: WVN | C29: ANR | D29: HAM | E29: STN | F29: RTM | G29: RTM | H29: HAM
C30: RTM | D30: ZEE | F30: HAM | H30: RTM
B32: Singapore | C32: Shanghai | D32: Port Klang | E32: Port Klang | F32: Yantian | G32: Colombo | H32: Singapore
B33: Shanghai | C33: Xingang | D33: Shanghai | E33: Ningbo | F33: Port Klang | G33: Singapore | H33: Xingang
B34: Ningbo | C34: Dalian | D34: Xiamen | E34: Pusan | F34: Shanghai | G34: Kaohsiung | H34: Ningbo
B35: Xiamen | C35: Qingdao | D35: Hong Kong | E35: Shanghai | F35: Ningbo | G35: Qingdao | H35: Shanghai
B36: Yantian | C36: Ningbo | D36: Yantian | G36: Shanghai | H36: Yantian
B37: Qingdao | G37: Ningbo
G38: Taipei
G39: Yantian
B43: !!! Rate inquiries - pls send your request to following contact !!!
B45: NVOQuotes@oocl.com
B47: Sales contacts Hamburg | F47: Sales contacts Bremen
B48: Name | C48: Phone | D48: E-Mail | F48: Name | G48: Phone | H48: E-Mail
B49: Anastasia Chernyshov | C49: 040 37 49 60 72 | D49: sales-baumann@OOCL.com | F49: Barbara Triep | G49: 0421 3018 872 | H49: Barbara.Triep@OOCL.com
B50: Andreas Erdmann | C50: 040 37 49 60 41 | D50: Andreas.Erdmann@OOCL.com | F50: Femke Opitz | G50: 0421 3018 776 | H50: Femke.Opitz@OOCL.com
B51: Carolin Albrecht | C51: 040 37 49 60 55 | D51: Carolin.Albrecht@OOCL.com | F51: Hendrik Seifert | G51: 0421 3018 842 | H51: Hendrik.Seifert@OOCL.com
B52: Chiara Hartwich | C52: 040 37 49 60 48 | D52: Chiara.Hartwich@OOCL.com | F52: Julius Blumenstein | G52: 0421 3018 819 | H52: Julius.Blumenstein@OOCL.com
B53: Christian Pick | C53: 040 37 49 60 39 | D53: Christian.Pick@OOCL.com | F53: Kristina Thoma | G53: 0421 3018 820 | H53: Kristina.Thoma@OOCL.com
B54: Finn Baumann | C54: 040 37 49 60 61 | D54: Finn.Baumann@OOCL.com | F54: Laura Nischik | G54: 040 3749 6070 | H54: Laura.Nischik@OOCL.com
B55: Franziska Winkler | C55: 040 37 49 60 59 | D55: Franziska.Winkler@OOCL.com | F55: Marina Gerwers | G55: 0421 3018 828 | H55: Marina.Gerwers@OOCL.com
B56: Jessica Gefcken | C56: 040 37 49 60 46 | D56: sales-winkler@OOCL.com | F56: Patrick Diederich | G56: 0421 3018 764 | H56: Patrick.Diederich@OOCL.com
B57: Jordi Villanes Erquinio | C57: 040 37 49 60 70 | D57: Jordi.Villanes.Erquinio@OOCL.com | F57: Simon Kremin | G57: 0421 3018 763 | H57: Simon.Kremin@OOCL.com
B58: Kerstin Grambow | C58: 040 37 49 60 43 | D58: Kerstin.Grambow@OOCL.com | F58: Thomas Otten | G58: 0421 3018 870 | H58: Thomas.Otten @OOCL.com
B59: Renate Kaut | C59: 040 37 49 60 64 | D59: Renate.Kaut@OOCL.com | F59: Tilman Schmitz | G59: 0421 3018 752 | H59: Tilman.Schmitz@OOCL.com
B60: Stefanie Glaser | C60: 040 37 49 60 54 | D60: Stefanie.Glaser@OOCL.com
B63: Booking contacts Hamburg | F63: Booking contacts Bremen
B65: HAMbooking.NVO@OOCL.com | F65: BREbooking.NVO@OOCL.com

Sheet Lookup
B1: Index | C1: Base Port | D1: Port Group 1 | E1: Region Group2
B2: =D2 -> DAM | C2: Dammam, Ash Sharqiyah, Saudi Arabia | D2: DAM | E2: MEAST
B3: =D3 -> FEBP | C3: Busan, South Korea | D3: FEBP | E3: n/a
B4: =D4 -> FEBP | C4: Dalian, Dalian, Liaoning, China | D4: FEBP | E4: NCHN
B5: =D5 -> FEBP | C5: Hong Kong, Hong Kong, China | D5: FEBP | E5: n/a
B6: =D6 -> FEBP | C6: Kaohsiung, Taiwan; Taipei, Taiwan | D6: FEBP | E6: n/a
B7: =D7 -> FEBP | C7: Nansha, Guangzhou, Guangdong, China | D7: FEBP | E7: n/a
B8: =D8 -> FEBP | C8: Ningbo, Ningbo, Zhejiang, China | D8: FEBP | E8: NCHN
B9: =D9 -> SIN/PKG | C9: Port Klang, Selangor, Malaysia | D9: SIN/PKG | E9: n/a
B10: =D10 -> FEBP | C10: Qingdao, Qingdao, Shandong, China | D10: FEBP | E10: NCHN
B11: =D11 -> FEBP | C11: Shanghai, China | D11: FEBP | E11: NCHN
B12: =D12 -> SIN/PKG | C12: Singapore, Singapore | D12: SIN/PKG | E12: n/a
B13: =D13 -> FEBP | C13: Taipei, Taiwan | D13: FEBP | E13: n/a
... B19: =D19 -> JED | C19: Jeddah, Makkah, Saudi Arabia | D19: JED | E19: MEAST
B20: FEBP | C20: Jakarta, Indonesia | D20: JKT | E20: n/a
B21: =D21 -> JPBP | C21: Kobe, Hyogo-ken, Japan | D21: JPBP | E21: n/a
B22: =D22 -> JPBP | C22: Yokohama, Kanagawa-ken, Japan | D22: JPBP | E22: n/a
B23: =D23 -> JPBP | C23: Tokyo, Japan | D23: JPBP | E23: n/a
B24: =D24 -> FEBP | C24: Kaohsiung, Taiwan | D24: FEBP | E24: n/a
E25: n/a
B26: =D26 -> SIN/PKG | C26: Port Klang, Selangor, Malaysia; Singapore, Singapore | D26: SIN/PKG | E26: Multiple | F26: * Filter Rechenblatt mit 'contains ;'
B27: =D27 -> FEBP | C27: Kaohsiung, Taiwan; Singapore, Singapore | D27: FEBP | E27: Multiple
B28: =D28 -> FEBP | C28: Ningbo, Ningbo, Zhejiang, China; Port Klang, Selangor, Malaysia | D28: FEBP | E28: Multiple
B29: =D29 -> FEBP | C29: Kaohsiung, Taiwan; Port Klang, Selangor, Malaysia; Singapore, Singapore | D29: FEBP | E29: Multiple
B30: =D30 -> FEBP | C30: Kaohsiung, Taiwan; Qingdao, Qingdao, Shandong, China | D30: FEBP | E30: Multiple
B31: =D31 -> FEBP | C31: Hong Kong, Hong Kong, China; Port Klang, Selangor, Malaysia; Singapore, Singapore | D31: FEBP | E31: Multiple
B32: =D32 -> FEBP | C32: Ningbo, Ningbo, Zhejiang, China; Shanghai, China | D32: FEBP | E32: Multiple
B33: =D33 -> FEBP | C33: Ningbo, Ningbo, Zhejiang, China; Qingdao, Qingdao, Shandong, China; Shanghai, China | D33: FEBP | E33: Multiple
B34: =D34 -> FEBP | C34: Hong Kong, Hong Kong, China; Yantian, Shenzhen, Guangdong, China | D34: FEBP | E34: Multiple
B35: =D35 -> FEBP | C35: Nansha, Guangzhou, Guangdong, China; Yantian, Shenzhen, Guangdong, China | D35: FEBP | E35: Multiple
B36: =D36 -> FEBP | C36: Hong Kong, Hong Kong, China; Port Klang, Selangor, Malaysia; Singapore, Singapore; Vung Tau, Ba Ria Vung Tau, Vietnam | D36: FEBP | E36: Multiple
B37: =D37 -> FEBP | C37: Hong Kong, Hong Kong, China; Nansha, Guangzhou, Guangdong, China | D37: FEBP | E37: Multiple
B38: =D38 -> FEBP | C38: Hong Kong, Hong Kong, China; Kaohsiung, Taiwan; Qingdao, Qingdao, Shandong, China | D38: FEBP | E38: Multiple
... B44: =D44 -> Abu Dhabi | C44: Abu Dhabi, Abu Zabi, United Arab Emirates | D44: Abu Dhabi | E44: MEAST
B45: JPBP | C45: Tokyo, Japan; Yokohama, Kanagawa-ken, Japan | D45: JPBP | E45: n/a
B46: FEBP | C46: Hong Kong, Hong Kong, China; Kaohsiung, Taiwan; Singapore, Singapore | D46: FEBP | E46: n/a
B47: FEBP | C47: Port Klang, Selangor, Malaysia; Shanghai, China | D47: FEBP | E47: Multiple
B48: FEBP | C48: Hong Kong, Hong Kong, China; Kaohsiung, Taiwan; Port Klang, Selangor, Malaysia | D48: FEBP | E48: Multiple
B49: JPBP | C49: Kobe, Hyogo-ken, Japan; Osaka, Japan | D49: JPBP | E49: n/a
B50: FEBP | C50: Hong Kong, Hong Kong, China; Nansha, Guangzhou, Guangdong, China; Shekou, Shenzhen, Guangdong, China; Yantian, Shenzhen, Guangdong, China | D50: FEBP | E50: n/a
B51: FEBP | C51: Hong Kong, Hong Kong, China; Nansha, Guangzhou, Guangdong, China; Shekou, Shenzhen, Guangdong, China; Yantian, Shenzhen, Guangdong, China | D51: FEBP | E51: n/a
B52: FEBP | C52: Shekou, Shenzhen, Guangdong, China; Yantian, Shenzhen, Guangdong, China | D52: FEBP | E52: n/a
B53: FEBP | C53: Hong Kong, Hong Kong, China; Nansha, Guangzhou, Guangdong, China; Shekou, Shenzhen, Guangdong, China; Yantian, Shenzhen, Guangdong, China | D53: FEBP | E53: n/a
B54: FEBP | C54: Hong Kong, Hong Kong, China; Nansha, Guangzhou, Guangdong, China; Shekou, Shenzhen, Guangdong, China; Yantian, Shenzhen, Guangdong, China | D54: FEBP | E54: n/a
B55: FEBP | C55: Hong Kong, Hong Kong, China; Nansha, Guangzhou, Guangdong, China; Shekou, Shenzhen, Guangdong, China; Yantian, Shenzhen, Guangdong, China | D55: FEBP | E55: n/a
B56: FEBP | C56: Hong Kong, Hong Kong, China; Nansha, Guangzhou, Guangdong, China; Shekou, Shenzhen, Guangdong, China | D56: FEBP | E56: n/a
... B70: FEBP | C70: Hong Kong, Hong Kong, China; | D70: FEBP | E70: n/a

Sheet Rechenblatt neu
B1: check ports under tab 'Lookup'
B2: direct calls - port group | C2: 20' | D2: 40' | E2: 40'HQ | J2: PUSAN TAD via NIN statt SHA
B3: FEBP | C3: 25 | D3: 25 | E3: 25 | G3: = NUR HIER EINTRAGEN
B4: DAM | C4: 925 | D4: 1125 | E4: 1125 | J4: Nhava via Colombo add on USD400/CTR
B5: JED
B6: JEA | C6: 575 | D6: 575 | E6: 575 | J6: Haldia | K6: 20GP = same rate as Kolkata
B7: HCM | C7: 175 | D7: 300 | E7: 300 | K7: 40'CTR = same rate as Kolkata
B8: JKT | C8: 300 | D8: 425 | E8: 425 | J8: Vizag | K8: Ratebuilder
B9: SIN/PKG | C9: =FEBP20 -> 25 | D9: =FEBP40 -> 25 | E9: =D9 -> 25 | J9: Kolkata | K9: Ratebuilder
B10: YOK | C10: 400 | D10: 400 | E10: 400
B11: JPBP | C11: 400 | D11: 400 | E11: 400
B12: Abu Dhabi | C12: 575 | D12: 575 | E12: 575 | J12: Forrestfield | K12: 20GP = + USD305
K13: 40'CTR = + USD405
B15: ABU DHABI nur IP1
A16: Middle East | G16: OVER (BP Rate) | H16: TAD20ft | I16: TAD40ft | J16: TAD40HQ | K16: Rate 20ft | L16: Rate 40ft | M16: Rate 40HQ
A17: Port group | B17: TAD's Far East vom Jul 24 - sortiert nach HUB-Port
A18: =VLOOKUP(G18,Lookup!C:D,2,0) -> JEA | B18: Ajman, United Arab Emirates | C18: CY | G18: Jebel Ali, Dubai, United Arab Emirates | H18: 300 | I18: 450 | J18: 450 | K18: =IF(H18<>"",VLOOKUP($A18,$B$3:$E$12,2,FALSE)+H18,"--") -> 875 | L18: =IF(I18<>"",VLOOKUP($A18,$B$3:$E$12,3,FALSE)+I18,"--") -> 1025 | M18: =L18 -> 1025
A19: =VLOOKUP(G19,Lookup!C:D,2,0) -> JEA | B19: Al Hidd, Muharraq Governorate, Bahrain | C19: CY | G19: Jebel Ali, Dubai, United Arab Emirates | H19: 250 | I19: 350 | J19: 350 | K19: =IF(H19<>"",VLOOKUP($A19,$B$3:$E$12,2,FALSE)+H19,"--") -> 825 | L19: =IF(I19<>"",VLOOKUP($A19,$B$3:$E$12,3,FALSE)+I19,"--") -> 925 | M19: =L19 -> 925
A20: JEA | B20: Al Shuwaikh, Al Asamah, Kuwait | C20: CY | G20: Jebel Ali, Dubai, United Arab Emirates | H20: 325 | I20: 575 | J20: 575 | K20: =IF(H20<>"",VLOOKUP($A20,$B$3:$E$12,2,FALSE)+H20,"--") -> 900 | L20: =IF(I20<>"",VLOOKUP($A20,$B$3:$E$12,3,FALSE)+I20,"--") -> 1150 | M20: =L20 -> 1150
A21: DAM | B21: Ar Riyad, Ar Riyad, Saudi Arabia | C21: CY | G21: Dammam, Ash Sharqiyah, Saudi Arabia | H21: 250 | I21: 450 | J21: 450 | K21: =IF(H21<>"",VLOOKUP($A21,$B$3:$E$12,2,FALSE)+H21,"--") -> 1175 | L21: =IF(I21<>"",VLOOKUP($A21,$B$3:$E$12,3,FALSE)+I21,"--") -> 1575 | M21: =L21 -> 1575
A22: =VLOOKUP(G22,Lookup!C:D,2,0) -> JEA | B22: Dammam, Ash Sharqiyah, Saudi Arabia | C22: CY | G22: Jebel Ali, Dubai, United Arab Emirates | H22: 350 | I22: 550 | J22: 550 | K22: =IF(H22<>"",VLOOKUP($A22,$B$3:$E$12,2,FALSE)+H22,"--") -> 925 | L22: =IF(I22<>"",VLOOKUP($A22,$B$3:$E$12,3,FALSE)+I22,"--") -> 1125 | M22: =L22 -> 1125
A23: =VLOOKUP(G23,Lookup!C:D,2,0) -> JEA | B23: Hamad port, Al Wakrah, Qatar | C23: CY | G23: Jebel Ali, Dubai, United Arab Emirates | H23: 375 | I23: 475 | J23: 475 | K23: =IF(H23<>"",VLOOKUP($A23,$B$3:$E$12,2,FALSE)+H23,"--") -> 950 | L23: =IF(I23<>"",VLOOKUP($A23,$B$3:$E$12,3,FALSE)+I23,"--") -> 1050 | M23: =L23 -> 1050
A24: =VLOOKUP(G24,Lookup!C:D,2,0) -> JEA | B24: Kuwait, Al Asamah, Kuwait | C24: CY | G24: Jebel Ali, Dubai, United Arab Emirates | H24: 325 | I24: 575 | J24: 575 | K24: =IF(H24<>"",VLOOKUP($A24,$B$3:$E$12,2,FALSE)+H24,"--") -> 900 | L24: =IF(I24<>"",VLOOKUP($A24,$B$3:$E$12,3,FALSE)+I24,"--") -> 1150 | M24: =L24 -> 1150
A25: =VLOOKUP(G25,Lookup!C:D,2,0) -> JEA | B25: Sharjah, United Arab Emirates | C25: CY | G25: Jebel Ali, Dubai, United Arab Emirates | H25: 150 | I25: 275 | J25: 275 | K25: =IF(H25<>"",VLOOKUP($A25,$B$3:$E$12,2,FALSE)+H25,"--") -> 725 | L25: =IF(I25<>"",VLOOKUP($A25,$B$3:$E$12,3,FALSE)+I25,"--") -> 850 | M25: =L25 -> 850
A26: =VLOOKUP(G26,Lookup!C:D,2,0) -> JEA | B26: Shuaiba, Al Ahmadi, Kuwait | C26: CY | G26: Jebel Ali, Dubai, United Arab Emirates | H26: 325 | I26: 550 | J26: 550 | K26: =IF(H26<>"",VLOOKUP($A26,$B$3:$E$12,2,FALSE)+H26,"--") -> 900 | L26: =IF(I26<>"",VLOOKUP($A26,$B$3:$E$12,3,FALSE)+I26,"--") -> 1125 | M26: =L26 -> 1125
A27: =VLOOKUP(G27,Lookup!C:D,2,0) -> JEA | B27: Sohar, Al Batinah North Governorate, Oman | C27: CY | G27: Jebel Ali, Dubai, United Arab Emirates | H27: 250 | I27: 350 | J27: 350 | K27: =IF(H27<>"",VLOOKUP($A27,$B$3:$E$12,2,FALSE)+H27,"--") -> 825 | L27: =IF(I27<>"",VLOOKUP($A27,$B$3:$E$12,3,FALSE)+I27,"--") -> 925 | M27: =L27 -> 925
A28: =VLOOKUP(G28,Lookup!C:D,2,0) -> JEA | B28: Umm Al Quwain, United Arab Emirates | C28: CY | G28: Jebel Ali, Dubai, United Arab Emirates | H28: 350 | I28: 600 | J28: 600 | K28: =IF(H28<>"",VLOOKUP($A28,$B$3:$E$12,2,FALSE)+H28,"--") -> 925 | L28: =IF(I28<>"",VLOOKUP($A28,$B$3:$E$12,3,FALSE)+I28,"--") -> 1175 | M28: =L28 -> 1175
B31: TAD's Far East vom Aug 24 - sortiert nach HUB-Port
A32: Asia Port Group | B32: Location | C32: Mode | D32: T/S Via | G32: OVER (BP Rate) | H32: TAD20ft | I32: TAD40ft | J32: TAD40HQ | K32: Rate 20ft | L32: Rate 40ft | M32: Rate 40HQ
A33: =VLOOKUP(G33,Lookup!C:D,2,0) -> JPBP | B33: Akita, Akita, Japan | C33: CY | D33: Hibiki, Fukuoka, Japan | E33: GC; DG | G33: Kobe, Hyogo-ken, Japan | H33: 550 | I33: 750 | J33: 750 | K33: =IF(H33<>"",VLOOKUP($A33,$B$3:$E$12,2,FALSE)+H33,"--") -> 950 | L33: =IF(I33<>"",VLOOKUP($A33,$B$3:$E$11,3,FALSE)+I33,"--") -> 1150 | M33: =IF(J33<>"",VLOOKUP($A33,$B$3:$E$11,4,FALSE)+J33,"--") -> 1150
A34: =VLOOKUP(G34,Lookup!C:D,2,0) -> FEBP | B34: Anji, Huzhou, Zhejiang, China | C34: CY | D34: Shanghai, China | E34: GC; DG | G34: Shanghai, China | H34: 175 | I34: 300 | J34: 300 | K34: =IF(H34<>"",VLOOKUP($A34,$B$3:$E$12,2,FALSE)+H34,"--") -> 200 | L34: =IF(I34<>"",VLOOKUP($A34,$B$3:$E$11,3,FALSE)+I34,"--") -> 325 | M34: =IF(J34<>"",VLOOKUP($A34,$B$3:$E$11,4,FALSE)+J34,"--") -> 325
A35: =VLOOKUP(G35,Lookup!C:D,2,0) -> FEBP | B35: Anqing, Anqing, Anhui, China | C35: CY | D35: Shanghai, China | E35: GC; DG | G35: Shanghai, China | H35: 200 | I35: 300 | J35: 300 | K35: =IF(H35<>"",VLOOKUP($A35,$B$3:$E$12,2,FALSE)+H35,"--") -> 225 | L35: =IF(I35<>"",VLOOKUP($A35,$B$3:$E$11,3,FALSE)+I35,"--") -> 325 | M35: =IF(J35<>"",VLOOKUP($A35,$B$3:$E$11,4,FALSE)+J35,"--") -> 325
A36: =VLOOKUP(G36,Lookup!C:D,2,0) -> SIN/PKG | B36: Bandar Lampung, Lampung, Indonesia | C36: CY | D36: Singapore, Singapore | E36: GC; DG | G36: Singapore, Singapore | H36: 425 | I36: 700 | J36: 700 | K36: =IF(H36<>"",VLOOKUP($A36,$B$3:$E$12,2,FALSE)+H36,"--") -> 450 | L36: =IF(I36<>"",VLOOKUP($A36,$B$3:$E$11,3,FALSE)+I36,"--") -> 725 | M36: =IF(J36<>"",VLOOKUP($A36,$B$3:$E$11,4,FALSE)+J36,"--") -> 725
A37: =VLOOKUP(G37,Lookup!C:D,2,0) -> SIN/PKG | B37: Bangkok, Thailand | C37: CY | D37: Port Klang, Selangor, Malaysia; Singapore, Singapore | E37: GC; DG | G37: Port Klang, Selangor, Malaysia; Singapore, Singapore | H37: 225 | I37: 350 | J37: 350 | K37: =IF(H37<>"",VLOOKUP($A37,$B$3:$E$12,2,FALSE)+H37,"--") -> 250 | L37: =IF(I37<>"",VLOOKUP($A37,$B$3:$E$11,3,FALSE)+I37,"--") -> 375 | M37: =IF(J37<>"",VLOOKUP($A37,$B$3:$E$11,4,FALSE)+J37,"--") -> 375
A38: =VLOOKUP(G38,Lookup!C:D,2,0) -> FEBP | B38: Beihai, Beihai, Guangxi, China | C38: CY | D38: Hong Kong, Hong Kong, China | E38: GC; DG | G38: Hong Kong, Hong Kong, China | H38: 350 | I38: 550 | J38: 550 | K38: =IF(H38<>"",VLOOKUP($A38,$B$3:$E$12,2,FALSE)+H38,"--") -> 375 | L38: =IF(I38<>"",VLOOKUP($A38,$B$3:$E$11,3,FALSE)+I38,"--") -> 575 | M38: =IF(J38<>"",VLOOKUP($A38,$B$3:$E$11,4,FALSE)+J38,"--") -> 575
A39: =VLOOKUP(G39,Lookup!C:D,2,0) -> FEBP | B39: Beijiao, Shunde, Guangdong, China | C39: CY | D39: Hong Kong, Hong Kong, China | E39: GC; DG | G39: Hong Kong, Hong Kong, China; Nansha, Guangzhou, Guangdong, China | H39: 125 | I39: 225 | J39: 225 | K39: =IF(H39<>"",VLOOKUP($A39,$B$3:$E$12,2,FALSE)+H39,"--") -> 150 | L39: =IF(I39<>"",VLOOKUP($A39,$B$3:$E$11,3,FALSE)+I39,"--") -> 250 | M39: =IF(J39<>"",VLOOKUP($A39,$B$3:$E$11,4,FALSE)+J39,"--") -> 250
A40: =VLOOKUP(G40,Lookup!C:D,2,0) -> SIN/PKG | B40: Belawan, Sumatera Utara, Indonesia | C40: CY | D40: Port Klang, Selangor, Malaysia; Singapore, Singapore | E40: GC; DG | G40: Port Klang, Selangor, Malaysia; Singapore, Singapore | H40: 300 | I40: 475 | J40: 475 | K40: =IF(H40<>"",VLOOKUP($A40,$B$3:$E$12,2,FALSE)+H40,"--") -> 325 | L40: =IF(I40<>"",VLOOKUP($A40,$B$3:$E$11,3,FALSE)+I40,"--") -> 500 | M40: =IF(J40<>"",VLOOKUP($A40,$B$3:$E$11,4,FALSE)+J40,"--") -> 500
A41: =VLOOKUP(G41,Lookup!C:D,2,0) -> SIN/PKG | B41: Bintulu, Sarawak, Malaysia | C41: CY | D41: Port Klang, Selangor, Malaysia | E41: GC; DG | G41: Port Klang, Selangor, Malaysia | H41: 750 | I41: 1350 | J41: 1350 | K41: =IF(H41<>"",VLOOKUP($A41,$B$3:$E$12,2,FALSE)+H41,"--") -> 775 | L41: =IF(I41<>"",VLOOKUP($A41,$B$3:$E$11,3,FALSE)+I41,"--") -> 1375 | M41: =IF(J41<>"",VLOOKUP($A41,$B$3:$E$11,4,FALSE)+J41,"--") -> 1375
A42: FEBP | B42: Bintulu, Sarawak, Malaysia | C42: CY | D42: Singapore, Singapore | E42: GC; DG | G42: Singapore, Singapore | H42: 1050 | I42: 1850 | J42: 1850 | K42: =IF(H42<>"",VLOOKUP($A42,$B$3:$E$12,2,FALSE)+H42,"--") -> 1075 | L42: =IF(I42<>"",VLOOKUP($A42,$B$3:$E$11,3,FALSE)+I42,"--") -> 1875 | M42: =IF(J42<>"",VLOOKUP($A42,$B$3:$E$11,4,FALSE)+J42,"--") -> 1875
A43: =VLOOKUP(G43,Lookup!C:D,2,0) -> FEBP | B43: Busan, South Korea | C43: CY | D43: Ningbo, Ningbo, Zhejiang, China | E43: GC; DG | G43: Ningbo, Ningbo, Zhejiang, China | H43: 45 | I43: 65 | J43: 65 | K43: =IF(H43<>"",VLOOKUP($A43,$B$3:$E$12,2,FALSE)+H43,"--") -> 70 | L43: =IF(I43<>"",VLOOKUP($A43,$B$3:$E$11,3,FALSE)+I43,"--") -> 90 | M43: =IF(J43<>"",VLOOKUP($A43,$B$3:$E$11,4,FALSE)+J43,"--") -> 90
A44: =VLOOKUP(G44,Lookup!C:D,2,0) -> FEBP | B44: Cebu City, Cebu, Philippines | C44: CY | D44: Kaohsiung, Taiwan | E44: GC; DG | G44: Kaohsiung, Taiwan | H44: 450 | I44: 775 | J44: 775 | K44: =IF(H44<>"",VLOOKUP($A44,$B$3:$E$12,2,FALSE)+H44,"--") -> 475 | L44: =IF(I44<>"",VLOOKUP($A44,$B$3:$E$11,3,FALSE)+I44,"--") -> 800 | M44: =IF(J44<>"",VLOOKUP($A44,$B$3:$E$11,4,FALSE)+J44,"--") -> 800
A45: =VLOOKUP(G45,Lookup!C:D,2,0) -> FEBP | B45: Changde, Changde, Hunan, China | C45: CY | D45: Shanghai, China | E45: GC; DG | G45: Shanghai, China | H45: 375 | I45: 700 | J45: 700 | K45: =IF(H45<>"",VLOOKUP($A45,$B$3:$E$12,2,FALSE)+H45,"--") -> 400 | L45: =IF(I45<>"",VLOOKUP($A45,$B$3:$E$11,3,FALSE)+I45,"--") -> 725 | M45: =IF(J45<>"",VLOOKUP($A45,$B$3:$E$11,4,FALSE)+J45,"--") -> 725
A46: =VLOOKUP(G46,Lookup!C:D,2,0) -> FEBP | B46: Changsha, Changsha, Hunan, China | C46: CY | D46: Shanghai, China | E46: GC; DG | G46: Shanghai, China | H46: 325 | I46: 550 | J46: 550 | K46: =IF(H46<>"",VLOOKUP($A46,$B$3:$E$12,2,FALSE)+H46,"--") -> 350 | L46: =IF(I46<>"",VLOOKUP($A46,$B$3:$E$11,3,FALSE)+I46,"--") -> 575 | M46: =IF(J46<>"",VLOOKUP($A46,$B$3:$E$11,4,FALSE)+J46,"--") -> 575
A47: =VLOOKUP(G47,Lookup!C:D,2,0) -> FEBP | B47: Changshu, Suzhou, Jiangsu, China | C47: CY | D47: Shanghai, China | E47: GC; DG | G47: Shanghai, China | H47: 175 | I47: 275 | J47: 275 | K47: =IF(H47<>"",VLOOKUP($A47,$B$3:$E$12,2,FALSE)+H47,"--") -> 200 | L47: =IF(I47<>"",VLOOKUP($A47,$B$3:$E$11,3,FALSE)+I47,"--") -> 300 | M47: =IF(J47<>"",VLOOKUP($A47,$B$3:$E$11,4,FALSE)+J47,"--") -> 300
A48: =VLOOKUP(G48,Lookup!C:D,2,0) -> FEBP | B48: Changzhou, Changzhou, Jiangsu, China | C48: CY | D48: Shanghai, China | E48: GC; DG | G48: Shanghai, China | H48: 175 | I48: 300 | J48: 300 | K48: =IF(H48<>"",VLOOKUP($A48,$B$3:$E$12,2,FALSE)+H48,"--") -> 200 | L48: =IF(I48<>"",VLOOKUP($A48,$B$3:$E$11,3,FALSE)+I48,"--") -> 325 | M48: =IF(J48<>"",VLOOKUP($A48,$B$3:$E$11,4,FALSE)+J48,"--") -> 325
A49: =VLOOKUP(G49,Lookup!C:D,2,0) -> FEBP | B49: Chengdu, Chengdu, Sichuan, China | C49: CY | D49: Shanghai, China | E49: GC; DG | G49: Shanghai, China | H49: 1250 | I49: 1600 | J49: 1600 | K49: =IF(H49<>"",VLOOKUP($A49,$B$3:$E$12,2,FALSE)+H49,"--") -> 1275 | L49: =IF(I49<>"",VLOOKUP($A49,$B$3:$E$11,3,FALSE)+I49,"--") -> 1625 | M49: =IF(J49<>"",VLOOKUP($A49,$B$3:$E$11,4,FALSE)+J49,"--") -> 1625
A50: =VLOOKUP(G50,Lookup!C:D,2,0) -> FEBP | B50: Chongqing, China | C50: CY | D50: Shanghai, China | E50: GC; DG | G50: Shanghai, China | H50: 400 | I50: 725 | J50: 725 | K50: =IF(H50<>"",VLOOKUP($A50,$B$3:$E$12,2,FALSE)+H50,"--") -> 425 | L50: =IF(I50<>"",VLOOKUP($A50,$B$3:$E$11,3,FALSE)+I50,"--") -> 750 | M50: =IF(J50<>"",VLOOKUP($A50,$B$3:$E$11,4,FALSE)+J50,"--") -> 750
A51: =VLOOKUP(G51,Lookup!C:D,2,0) -> SIN/PKG | B51: Da Nang, Vietnam | C51: CY | D51: Singapore, Singapore | E51: GC; DG | G51: Singapore, Singapore | H51: 875 | I51: 1550 | J51: 1550 | K51: =IF(H51<>"",VLOOKUP($A51,$B$3:$E$12,2,FALSE)+H51,"--") -> 900 | L51: =IF(I51<>"",VLOOKUP($A51,$B$3:$E$11,3,FALSE)+I51,"--") -> 1575 | M51: =IF(J51<>"",VLOOKUP($A51,$B$3:$E$11,4,FALSE)+J51,"--") -> 1575
A52: =VLOOKUP(G52,Lookup!C:D,2,0) -> FEBP | B52: Dafeng, Yancheng, Jiangsu, China | C52: CY | D52: Shanghai, China | E52: GC; DG | G52: Shanghai, China | H52: 225 | I52: 350 | J52: 350 | K52: =IF(H52<>"",VLOOKUP($A52,$B$3:$E$12,2,FALSE)+H52,"--") -> 250 | L52: =IF(I52<>"",VLOOKUP($A52,$B$3:$E$11,3,FALSE)+I52,"--") -> 375 | M52: =IF(J52<>"",VLOOKUP($A52,$B$3:$E$11,4,FALSE)+J52,"--") -> 375
A53: =VLOOKUP(G53,Lookup!C:D,2,0) -> SIN/PKG | B53: Davao City, Davao del Sur, Philippines | C53: CY | D53: Singapore, Singapore | E53: GC; DG | G53: Singapore, Singapore | H53: 950 | I53: 1750 | J53: 1750 | K53: =IF(H53<>"",VLOOKUP($A53,$B$3:$E$12,2,FALSE)+H53,"--") -> 975 | L53: =IF(I53<>"",VLOOKUP($A53,$B$3:$E$11,3,FALSE)+I53,"--") -> 1775 | M53: =IF(J53<>"",VLOOKUP($A53,$B$3:$E$11,4,FALSE)+J53,"--") -> 1775
A54: =VLOOKUP(G54,Lookup!C:D,2,0) -> FEBP | B54: Dongguan, Dongguan, Guangdong, China | C54: CY | D54: Hong Kong, Hong Kong, China; Yantian, Shenzhen, Guangdong, China | E54: GC; DG | G54: Hong Kong, Hong Kong, China; Nansha, Guangzhou, Guangdong, China; Shekou, Shenzhen, Guangdong, China; Yantian, Shenzhen, Guangdong, China | H54: 200 | I54: 325 | J54: 325 | K54: =IF(H54<>"",VLOOKUP($A54,$B$3:$E$12,2,FALSE)+H54,"--") -> 225 | L54: =IF(I54<>"",VLOOKUP($A54,$B$3:$E$11,3,FALSE)+I54,"--") -> 350 | M54: =IF(J54<>"",VLOOKUP($A54,$B$3:$E$11,4,FALSE)+J54,"--") -> 350
... A227: =VLOOKUP(G227,Lookup!C:D,2,0) -> FEBP | B227: Zhuhai, Zhuhai, Guangdong, China | C227: CY | D227: Hong Kong, Hong Kong, China; Yantian, Shenzhen, Guangdong, China | E227: GC; DG | G227: Hong Kong, Hong Kong, China; Yantian, Shenzhen, Guangdong, China | H227: 225 | I227: 350 | J227: 350 | K227: =IF(H227<>"",VLOOKUP($A227,$B$3:$E$12,2,FALSE)+H227,"--") -> 250 | L227: =IF(I227<>"",VLOOKUP($A227,$B$3:$E$11,3,FALSE)+I227,"--") -> 375 | M227: =IF(J227<>"",VLOOKUP($A227,$B$3:$E$11,4,FALSE)+J227,"--") -> 375

Sheet Far East+Japan
B3: Orient Overseas Container Line Ltd.
B4: =Introduction!D8 -> NEW: rate reference mentioned in your email
B5: =Introduction!B9 -> valid as from 01.12.2025 - 31.01.2026
B9: Far East direct calls | C9: GATE IN subject to below + destination charges
B10: POL | C10: POD | D10: 20' Box | E10: 40' Box | F10: 40' HQ | G10: GC;DG | H10: Loop
B11: HAM / RTM / ANR | C11: Dalian | D11: ='Rechenblatt neu'!FEBP20 -> 25 | E11: ='Rechenblatt neu'!FEBP40 -> 25 | F11: ='Rechenblatt neu'!FEBPHQ -> 25 | G11: GC;DG | H11: LL2
B12: HAM / RTM / ZEE | C12: Hong Kong | D12: ='Rechenblatt neu'!FEBP20 -> 25 | E12: ='Rechenblatt neu'!FEBP40 -> 25 | F12: ='Rechenblatt neu'!FEBPHQ -> 25 | G12: GC;DG | H12: LL3
B13: HAM / RTM | C13: Kaohsiung | D13: ='Rechenblatt neu'!FEBP20 -> 25 | E13: ='Rechenblatt neu'!FEBP40 -> 25 | F13: ='Rechenblatt neu'!FEBPHQ -> 25 | G13: GC;DG | H13: LL6
B14: HAM / WVN / RTM / ANR / ZEE | C14: Nansha ( in t/s via PKG/SIN) | D14: ='Rechenblatt neu'!FEBP20 -> 25 | E14: ='Rechenblatt neu'!FEBP40 -> 25 | F14: ='Rechenblatt neu'!FEBPHQ -> 25 | G14: GC;DG | H14: LL1; LL3; LL5; LL6; LL7
B15: HAM / WVN / RTM / ANR / ZEE | C15: Ningbo | D15: ='Rechenblatt neu'!FEBP20 -> 25 | E15: ='Rechenblatt neu'!FEBP40 -> 25 | F15: ='Rechenblatt neu'!FEBPHQ -> 25 | G15: GC;DG | H15: LL1; LL2; LL5; LL6; LL7
B16: HAM / RTM / ANR | C16: Port Klang | D16: ='Rechenblatt neu'!FEBP20 -> 25 | E16: ='Rechenblatt neu'!FEBP40 -> 25 | F16: ='Rechenblatt neu'!FEBPHQ -> 25 | G16: GC;DG | H16: LL3; LL5
B17: HAM / WVN / RTM / ANR / ZEE | C17: Qingdao | D17: ='Rechenblatt neu'!FEBP20 -> 25 | E17: ='Rechenblatt neu'!FEBP40 -> 25 | F17: ='Rechenblatt neu'!FEBPHQ -> 25 | G17: GC;DG | H17: LL1; LL2; LL6
B18: HAM / WVN / RTM / ANR / ZEE | C18: Shanghai | D18: ='Rechenblatt neu'!FEBP20 -> 25 | E18: ='Rechenblatt neu'!FEBP40 -> 25 | F18: ='Rechenblatt neu'!FEBPHQ -> 25 | G18: GC;DG | H18: LL1; LL3; LL2; LL6; LL7
B19: HAM / WVN / RTM / ANR / ZEE | C19: Shekou ( in t/s via PKG/SIN) | D19: ='Rechenblatt neu'!FEBP20 -> 25 | E19: ='Rechenblatt neu'!FEBP40 -> 25 | F19: ='Rechenblatt neu'!FEBPHQ -> 25 | G19: GC;DG | H19: LL1; LL3; LL5; LL6; LL7
B20: HAM / WVN / RTM / ANR / ZEE | C20: Singapore | D20: ='Rechenblatt neu'!FEBP20 -> 25 | E20: ='Rechenblatt neu'!FEBP40 -> 25 | F20: ='Rechenblatt neu'!FEBPHQ -> 25 | G20: GC;DG | H20: LL1; LL6; LL7
B21: HAM / RTM | C21: Taipei | D21: ='Rechenblatt neu'!FEBP20 -> 25 | E21: ='Rechenblatt neu'!FEBP40 -> 25 | F21: ='Rechenblatt neu'!FEBPHQ -> 25 | G21: GC;DG | H21: LL6
B22: WVN / ZEE / HAM / RTM | C22: Xiamen | D22: ='Rechenblatt neu'!FEBP20 -> 25 | E22: ='Rechenblatt neu'!FEBP40 -> 25 | F22: ='Rechenblatt neu'!FEBPHQ -> 25 | G22: GC;DG | H22: LL1; LL3
... B24: HAM / WVN / RTM / ANR / ZEE | C24: Yantian | D24: ='Rechenblatt neu'!FEBP20 -> 25 | E24: ='Rechenblatt neu'!FEBP40 -> 25 | F24: ='Rechenblatt neu'!FEBPHQ -> 25 | G24: GC;DG | H24: LL1; LL3; LL5; LL6; LL7
B26: Freetime at Origin for destination CHINA / INDONESIA / SINGAPORE / MALAYSIA / TAIWAN / VIETNAM / THAILAND
B27: ANR / RTM / WHV / ZEE / HAM : 14 cal days DD combined (2in1)
B29: Freetime at Destination:
B30: CHINA / INDONESIA / SINGAPORE / VIETNAM / HONG KONG : 14 cal days DD combined (2in1)
B31: MALAYSIA / TAIWAN / THAILAND : 14 cal days DETENTION - sub to QUAY RENT
B33: Far East direct calls & transshipments | C33: GATE IN subject to below + destination charges (all charges prepaid!)
B34: POL | C34: POD | D34: 20' Box | E34: 40' Box | F34: 40' HQ | G34: GC;DG | H34: Loop
B35: WVN / HAM / ZEE / RTM | C35: Chattogram (via Port Klang / Singapore / Colombo) | D35: 1300 | E35: 1600 | F35: 1600 | G35: GC;DG | H35: LL1; LL3; LL5; LL6; LL7
B36: HAM / RTM | C36: Colombo | D36: 550 | E36: 550 | F36: 550 | G36: GC;DG | H36: LL6
B38: Japan via transshipment | C38: GATE IN subject to below + destination charges
B39: POL | C39: POD | D39: 20' Box | E39: 40' Box | F39: 40' HQ | G39: GC;DG | H39: Loop
B40: WVN / HAM / RTM / ANR / ZEE | C40: Tokyo | D40: ='Rechenblatt neu'!$C11 -> 400 | E40: ='Rechenblatt neu'!D11 -> 400 | F40: =E40 -> 400 | G40: GC;DG | H40: LL1; LL2 ; LL3; LL5; LL6; LL7
B41: WVN / HAM / RTM / ANR / ZEE | C41: Kobe | D41: =D40 -> 400 | E41: =E40 -> 400 | F41: =E41 -> 400 | G41: GC;DG | H41: LL1; LL2 ; LL3; LL5; LL6; LL7
B42: WVN / HAM / RTM / ANR / ZEE | C42: Nagoya | D42: =D41 -> 400 | E42: =E41 -> 400 | F42: =E42 -> 400 | G42: GC;DG | H42: LL1; LL2 ; LL3; LL5; LL6; LL7
B43: WVN / HAM / RTM / ANR / ZEE | C43: Yokohama | D43: =D42 -> 400 | E43: =E42 -> 400 | F43: =E43 -> 400 | G43: GC;DG | H43: LL1; LL2 ; LL3; LL5; LL6; LL7
B44: WVN / HAM / RTM / ANR / ZEE | C44: Osaka | D44: =D43 -> 400 | E44: =E42 -> 400 | F44: =E44 -> 400 | G44: GC;DG | H44: LL1; LL2 ; LL3; LL5; LL6; LL7
B46: Far East Wing Ports | C46: GATE IN subject to below + destination charges
B47: POD | C47: transshipment via | D47: 20' Box | E47: 40' Box | F47: 40' HQ | G47: GC;DG
B48: Akita, Akita, Japan | C48: Hibiki, Fukuoka, Japan | D48: 950 | E48: 1150 | F48: 1150 | G48: GC; DG
B49: Anji, Huzhou, Zhejiang, China | C49: Shanghai, China | D49: 200 | E49: 325 | F49: 325 | G49: GC; DG
B50: Anqing, Anqing, Anhui, China | C50: Shanghai, China | D50: 225 | E50: 325 | F50: 325 | G50: GC; DG
B51: Bandar Lampung, Lampung, Indonesia | C51: Singapore, Singapore | D51: 450 | E51: 725 | F51: 725 | G51: GC; DG
B52: Bangkok, Thailand | C52: Port Klang, Selangor, Malaysia; Singapore, Singapore | D52: 250 | E52: 375 | F52: 375 | G52: GC; DG
B53: Beihai, Beihai, Guangxi, China | C53: Hong Kong, Hong Kong, China | D53: 375 | E53: 575 | F53: 575 | G53: GC; DG
B54: Beijiao, Shunde, Guangdong, China | C54: Hong Kong, Hong Kong, China | D54: 150 | E54: 250 | F54: 250 | G54: GC; DG
B55: Belawan, Sumatera Utara, Indonesia | C55: Port Klang, Selangor, Malaysia; Singapore, Singapore | D55: 325 | E55: 500 | F55: 500 | G55: GC; DG
B56: Bintulu, Sarawak, Malaysia | C56: Port Klang, Selangor, Malaysia | D56: 775 | E56: 1375 | F56: 1375 | G56: GC; DG
B57: Bintulu, Sarawak, Malaysia | C57: Singapore, Singapore | D57: 1075 | E57: 1875 | F57: 1875 | G57: GC; DG
B58: Busan, South Korea | C58: Ningbo, Ningbo, Zhejiang, China | D58: 70 | E58: 90 | F58: 90 | G58: GC; DG
B59: Cebu City, Cebu, Philippines | C59: Kaohsiung, Taiwan | D59: 475 | E59: 800 | F59: 800 | G59: GC; DG
... B95: Hiroshima, Japan | C95: Kobe, Hyogo-ken, Japan | D95: 850 | E95: 1025 | F95: 1025 | G95: GC; DG
B96: Ho Chi Minh, Vietnam | C96: Port Klang, Selangor, Malaysia; Singapore, Singapore | D96: 175 | E96: 300 | F96: 300 | G96: GC; DG | H96: !! No DG acceptance in Cat Lai !!
B97: Hososhima, Miyazaki, Japan | C97: Kobe, Hyogo-ken, Japan | D97: 750 | E97: 850 | F97: 850 | G97: GC; DG
B98: Huadu, Guangzhou, Guangdong, China | C98: Hong Kong, Hong Kong, China; Yantian, Shenzhen, Guangdong, China | D98: 175 | E98: 275 | F98: 275 | G98: GC; DG
B99: Huangpu, Guangzhou, Guangdong, China | C99: Hong Kong, Hong Kong, China; Yantian, Shenzhen, Guangdong, China | D99: 225 | E99: 300 | F99: 300 | G99: GC; DG
B100: Huangshigang, Huangshi, Hubei, China | C100: Shanghai, China | D100: 225 | E100: 325 | F100: 325 | G100: GC; DG
B101: Imabari, Ehime, Japan | C101: Kobe, Hyogo-ken, Japan | D101: 800 | E101: 1000 | F101: 1000 | G101: GC; DG
B102: Imari, Saga, Japan | C102: Kobe, Hyogo-ken, Japan | D102: 800 | E102: 1000 | F102: 1000 | G102: GC; DG
B103: Iwakuni, Yamaguchi, Japan | C103: Kobe, Hyogo-ken, Japan | D103: 750 | E103: 950 | F103: 950 | G103: GC; DG
B104: Iyomishima (Shikokuchuo), Ehime, Japan | C104: Kobe, Hyogo-ken, Japan | D104: 800 | E104: 1000 | F104: 1000 | G104: GC; DG
B105: Jakarta, Indonesia | C105: Port Klang, Selangor, Malaysia; Singapore, Singapore | D105: 300 | E105: 425 | F105: 425 | G105: GC; DG
B106: Jiangmen, Jiangmen, Guangdong, China | C106: Hong Kong, Hong Kong, China | D106: 175 | E106: 250 | F106: 250 | G106: GC; DG
B107: Jiangmen, Jiangmen, Guangdong, China | C107: Yantian, Shenzhen, Guangdong, China | D107: 250 | E107: 400 | F107: 400 | G107: GC; DG
B108: Jiangyin, Fuqing, Fuzhou, Fujian, China | C108: Kaohsiung, Taiwan | D108: 300 | E108: 450 | F108: 450 | G108: GC; DG
... B240: Zhuhai, Zhuhai, Guangdong, China | C240: Hong Kong, Hong Kong, China; Yantian, Shenzhen, Guangdong, China | D240: 250 | E240: 375 | F240: 375 | G240: GC; DG
B241: *Only accept couple of 20'GP rail T/S via Shanghai to FND Hefei, Xi'an, Zhengzhou, Mianyang, Chengdu, Nanchang,Shenyang,Changchun,Harbin
B242: For single 20GP over 6 ton, Ctr will stay at Shanghai/Qingdao for a long time (usually at least 3 weeks).
B243: Occuring extra costs have to be absorbed by shipper or consignee
B247: Included charges: BAF; CAF; CWC; CWX; EMS; ETS; GAS; LSA; SUZ; THC; IFP
B248: -------------------------------------------
B249: plus following surcharges, valid until further notice
B251: MBF: | C251: EUR 40,- per booking (for non-Electronic Booking Instruction, except bookings to Russia until further notice)
B252: DOC: | C252: EUR 75,- per B/L (applies for non-Electronic Shipping Instruction only (Documentation -> Shipping Instructions) via My OOCL.com)
B253: AMS: | C253: EUR 25,- per B/L - shipments to/via Japan/China
B254: IMO: | C254: USD 100,- per CTR (dry) subject to PSA costs if transshipped via Singapore (subject to acceptance) ; except Malaysia
B255: IMO to/via Port Kelang: | C255: USD 150,-/200,-/200,- per 20’/40’/40’HQ DRY - subject to acceptance
B256: CLE Colombo (Cleaning Fee): | C256: USD 10,- per TEU prepaid
B257: CLE Chattogram (Cleaning Fee): | C257: BDT 500,- per CTR prepaid
B259: Plus origin charges (all listed on www.oocl.com/eng/resourcecenter/globalinfo/Pages/default.aspx )
B260: Plus destination charges (all listed on www.oocl.com/eng/resourcecenter/globalinfo/Pages/default.aspx )
B262: For your PSA Group (to/via Singapore) please check with local OOCL Customer Service
B264: PSA costs = DHT tariff per 20’/40’/45’ for DG t/s via SIN valid till 31.01.2026
B265: · PSA 3/2F/2S: SGD 180/360/405
B266: · PSA 2B/2C: SGD 930/1485/1643
B267: · PSA 2A: SGD 1080/1635/1793
B268: · PSA 1S: SGD 380/560/605
B269: · PSA 1C/1N: SGD 1130/1685/1843
B270: · PSA 1/1D: SGD 1490/2405/2653
B271: · PSA 2 (UN1057 only): SGD 1690/2605/2853
B272: · PSA 2 (except UN1057): SGD 1290/2205/2453
B275: PSA costs = DHT tariff per 20’/40’/45’ for DG t/s via SIN as from 01.02.2026
B276: PSA Dangerous Good Group | C276: per 20/40' CTR
B277: 3/2F/2S | C277: USD 140/280
B278: 2B/2S | C278: USD 730/1160
B279: 2A | C279: USD 850/1280
B280: 1S | C280: USD 305/445
B281: 1C/1N | C281: USD 890/1320
B282: 2 - lighter UN1057 | C282: USD 1325/2030
B283: 2 - except for lighter UN1057 | C283: USD 1010/1720
B284: 1/1D | C284: USD 1165/1875
B286: DG via Port Klang:
B287: Please check the acceptance of dangerous goods for transshipment in Port Kelang.
...

Sheet LookupK
B1: Index | C1: Base Port | D1: Port Group 1 | E1: Region Group2
B2: =D2 -> FEBP | C2: Busan, South Korea | D2: FEBP | E2: n/a
B3: =D3 -> FEBP | C3: Nansha, Guangzhou, Guangdong, China | D3: FEBP | E3: n/a
B4: =D4 -> FEBP | C4: Ningbo, Ningbo, Zhejiang, China | D4: FEBP | E4: NCHN
B5: =D5 -> FEBP | C5: Port Klang, Selangor, Malaysia | D5: FEBP | E5: n/a
B6: =D6 -> FEBP | C6: Shanghai, China | D6: FEBP | E6: NCHN
B7: =D7 -> FEBP | C7: Shekou, Shenzhen, Guangdong, China | D7: FEBP | E7: n/a
B8: =D8 -> JED | C8: Jeddah, Makkah, Saudi Arabia | D8: JED | E8: MEAST
B9: =D9 -> FEBP | C9: Hong Kong, Hong Kong; Kaohsiung, Taiwan; Port Klang, Selangor, Malaysia; Singapore, Singapore | D9: FEBP | E9: Multiple | G9: * Filter Rechenblatt mit 'contains ;'
B10: =D10 -> FEBP | C10: Ningbo, Ningbo, Zhejiang, China; Port Klang, Selangor, Malaysia | D10: FEBP | E10: Multiple
B11: =D11 -> FEBP | C11: Qingdao, Qingdao, Shandong, China; Shanghai, China | D11: FEBP | E11: Multiple
B12: =D12 -> FEBP | C12: Hong Kong, Hong Kong; Nansha, Guangzhou, Guangdong, China | D12: FEBP | E12: Multiple
B13: =D13 -> FEBP | C13: Ningbo, Ningbo, Zhejiang, China; Port Klang, Selangor, Malaysia | D13: FEBP | E13: Multiple
B14: FEBP | C14: Port Klang, Selangor, Malaysia; Shekou, Shenzhen, Guangdong, China | D14: FEBP | E14: Multiple
B15: =D15 -> FEBP | C15: Hong Kong, Hong Kong; Shekou, Shenzhen, Guangdong, China | D15: FEBP | E15: Multiple
B16: =D16 -> FEBP | C16: Nansha, Guangzhou, Guangdong, China; Yantian, Shenzhen, Guangdong, China | D16: FEBP | E16: Multiple
B17: =D17 -> FEBP | C17: Ningbo, Ningbo, Zhejiang, China; Shanghai, China | D17: FEBP | E17: Multiple
B18: =D18 -> FEBP | C18: Port Klang, Selangor, Malaysia; Singapore, Singapore | D18: FEBP | E18: Multiple
B19: =D19 -> FEBP | C19: Port Klang, Selangor, Malaysia; Shanghai, China | D19: FEBP | E19: Multiple
B20: =D20 -> FEBP | C20: Ningbo, Ningbo, Zhejiang, China; Shanghai, China | D20: FEBP | E20: Multiple
B21: =D21 -> HKG | C21: Hong Kong, Hong Kong, China | D21: HKG | E21: n/a
B22: =D22 -> SIN | C22: Singapore, Singapore | D22: SIN | E22: n/a
B23: =D23 -> FEBP | C23: Yantian, Shenzhen, Guangdong, China | D23: FEBP | E23: n/a
B24: FEBP | C24: Hong Kong, Hong Kong, China; Nansha, Guangzhou, Guangdong, China; Shekou, Shenzhen, Guangdong, China; Yantian, Shenzhen, Guangdong, China | D24: FEBP | E24: Multiple
B25: FEBP | C25: Ningbo, Ningbo, Zhejiang, China; Xiamen, Xiamen, Fujian, China | D25: FEBP | E25: n/a
B26: FEBP | C26: Kaohsiung, Taiwan; Port Klang, Selangor, Malaysia; Singapore, Singapore | D26: FEBP | E26: Multiple
B27: FEBP | C27: Hong Kong, Hong Kong, China; Nansha, Guangzhou, Guangdong, China; Shekou, Shenzhen, Guangdong, China | D27: FEBP | E27: Multiple
B28: FEBP | C28: Shekou, Shenzhen, Guangdong, China; Yantian, Shenzhen, Guangdong, China | D28: FEBP | E28: Multiple
B29: FEBP | C29: Ningbo, Ningbo, Zhejiang, China; Qingdao, Qingdao, Shandong, China; Shanghai, China | D29: FEBP | E29: Multiple
B30: FEBP | C30: Nansha, Guangzhou, Guangdong, China; Shekou, Shenzhen, Guangdong, China; Yantian, Shenzhen, Guangdong, China | D30: FEBP | E30: Multiple
B31: FEBP | C31: Nansha, Guangzhou, Guangdong, China; Shekou, Shenzhen, Guangdong, China | D31: FEBP | E31: Multiple
B32: FEBP | C32: Kaohsiung, Taiwan; Port Klang, Selangor, Malaysia | D32: FEBP | E32: Multiple
B33: FEBP | C33: Kaohsiung, Taiwan; Taipei, Taiwan | D33: FEBP | E33: Multiple
B34: FEBP | C34: Xingang, Tianjin, China | D34: FEBP | E34: Multiple
B35: FEBP | C35: Hong Kong, Hong Kong, China; Kaohsiung, Taiwan; Port Klang, Selangor, Malaysia | D35: FEBP | E35: Multiple
... B89: FEBP | C89: Hong Kong, Hong Kong, China; Nansha, Guangzhou, Guangdong, China; Shekou, Shenzhen, Guangdong, China; Yantian, Shenzhen, Guangdong, China | D89: FEBP | E89: Multiple

Sheet Rechenblatt Koper neu
B1: check ports under tab 'LookupK'
B2: direct calls - port group | C2: 20' | D2: 40' | E2: 40'HQ
B3: FEBP | C3: 50 | D3: 75 | E3: 75 | G3: = NUR HIER EINTRAGEN
G4: = DO NOT TOUCH!
B5: JED | C5: 550 | D5: 725 | E5: 725
B7: HKG | C7: 100 | D7: 175 | E7: 175 | G7: Dalian , Xingang nicht bei Over Ports?
B8: SIN | C8: 100 | D8: 175 | E8: 175
K11: 2 | L11: 3 | M11: 4
A12: Middle East | G12: OVER (BP Rate) | H12: TAD20ft | I12: TAD40ft | J12: TAD40HQ | K12: Rate 20ft | L12: Rate 40ft | M12: Rate 40HQ
A13: Port group | B13: TAD's Far East vom Aug 2018 - sortiert nach HUB-Port
A14: =VLOOKUP(G14,[1]LookupK!C:D,2,0) -> JED | B14: Al 'Aqabah, Jordan | C14: CY | G14: Jeddah, Makkah, Saudi Arabia | H14: 400 | I14: 600 | J14: 600 | K14: =IF(H14<>"",VLOOKUP($A14,$B$3:$E$10,2,FALSE)+H14,"--") -> 950 | L14: =IF(I14<>"",VLOOKUP($A14,$B$3:$E$10,3,FALSE)+I14,"--") -> 1325 | M14: =IF(J14<>"",VLOOKUP($A14,$B$3:$E$10,4,FALSE)+J14,"--") -> 1325
B20: TAD's Far East vom May 2025 - sortiert nach HUB-Port
A21: Asia Port Group | B21: Location | C21: Mode | D21: T/S Via | G21: OVER (BP Rate) | H21: TAD20ft | I21: TAD40ft | J21: TAD40HQ | K21: Rate 20ft | L21: Rate 40ft | M21: Rate 40HQ
A22: =VLOOKUP(G22,LookupK!C:D,2,0) -> FEBP | B22: Anji, Huzhou, Zhejiang, China | C22: CY | D22: Shanghai, China | E22: GC; DG | G22: Shanghai, China | H22: 175 | I22: 300 | J22: 300 | K22: =IF(H22<>"",VLOOKUP($A22,$B$3:$E$10,2,FALSE)+H22,"--") -> 225 | L22: =IF(I22<>"",VLOOKUP($A22,$B$3:$E$10,3,FALSE)+I22,"--") -> 375 | M22: =IF(J22<>"",VLOOKUP($A22,$B$3:$E$10,4,FALSE)+J22,"--") -> 375
A23: =VLOOKUP(G23,LookupK!C:D,2,0) -> FEBP | B23: Anqing, Anqing, Anhui, China | C23: CY | D23: Shanghai, China | E23: GC; DG | G23: Shanghai, China | H23: 200 | I23: 300 | J23: 300 | K23: =IF(H23<>"",VLOOKUP($A23,$B$3:$E$10,2,FALSE)+H23,"--") -> 250 | L23: =IF(I23<>"",VLOOKUP($A23,$B$3:$E$10,3,FALSE)+I23,"--") -> 375 | M23: =IF(J23<>"",VLOOKUP($A23,$B$3:$E$10,4,FALSE)+J23,"--") -> 375
A24: =VLOOKUP(G24,LookupK!C:D,2,0) -> FEBP | B24: Bangkok, Thailand | C24: CY | D24: Port Klang, Selangor, Malaysia | E24: GC; DG | G24: Port Klang, Selangor, Malaysia | H24: 225 | I24: 350 | J24: 350 | K24: =IF(H24<>"",VLOOKUP($A24,$B$3:$E$10,2,FALSE)+H24,"--") -> 275 | L24: =IF(I24<>"",VLOOKUP($A24,$B$3:$E$10,3,FALSE)+I24,"--") -> 425 | M24: =IF(J24<>"",VLOOKUP($A24,$B$3:$E$10,4,FALSE)+J24,"--") -> 425
A25: =VLOOKUP(G25,LookupK!C:D,2,0) -> FEBP | B25: Belawan, Sumatera Utara, Indonesia | C25: CY | D25: Port Klang, Selangor, Malaysia | E25: GC; DG | G25: Port Klang, Selangor, Malaysia | H25: 300 | I25: 475 | J25: 475 | K25: =IF(H25<>"",VLOOKUP($A25,$B$3:$E$10,2,FALSE)+H25,"--") -> 350 | L25: =IF(I25<>"",VLOOKUP($A25,$B$3:$E$10,3,FALSE)+I25,"--") -> 550 | M25: =IF(J25<>"",VLOOKUP($A25,$B$3:$E$10,4,FALSE)+J25,"--") -> 550
A26: =VLOOKUP(G26,LookupK!C:D,2,0) -> FEBP | B26: Bintulu, Sarawak, Malaysia | C26: CY | D26: Port Klang, Selangor, Malaysia | E26: GC; DG | G26: Port Klang, Selangor, Malaysia | H26: 750 | I26: 1350 | J26: 1350 | K26: =IF(H26<>"",VLOOKUP($A26,$B$3:$E$10,2,FALSE)+H26,"--") -> 800 | L26: =IF(I26<>"",VLOOKUP($A26,$B$3:$E$10,3,FALSE)+I26,"--") -> 1425 | M26: =IF(J26<>"",VLOOKUP($A26,$B$3:$E$10,4,FALSE)+J26,"--") -> 1425
A27: =VLOOKUP(G27,LookupK!C:D,2,0) -> FEBP | B27: Busan, South Korea | C27: CY | D27: Shanghai, China | E27: GC; DG | G27: Shanghai, China | H27: 45 | I27: 65 | J27: 65 | K27: =IF(H27<>"",VLOOKUP($A27,$B$3:$E$10,2,FALSE)+H27,"--") -> 95 | L27: =IF(I27<>"",VLOOKUP($A27,$B$3:$E$10,3,FALSE)+I27,"--") -> 140 | M27: =IF(J27<>"",VLOOKUP($A27,$B$3:$E$10,4,FALSE)+J27,"--") -> 140
A28: =VLOOKUP(G28,LookupK!C:D,2,0) -> FEBP | B28: Changde, Changde, Hunan, China | C28: CY | D28: Shanghai, China | E28: GC; DG | G28: Shanghai, China | H28: 375 | I28: 700 | J28: 700 | K28: =IF(H28<>"",VLOOKUP($A28,$B$3:$E$10,2,FALSE)+H28,"--") -> 425 | L28: =IF(I28<>"",VLOOKUP($A28,$B$3:$E$10,3,FALSE)+I28,"--") -> 775 | M28: =IF(J28<>"",VLOOKUP($A28,$B$3:$E$10,4,FALSE)+J28,"--") -> 775
A29: =VLOOKUP(G29,LookupK!C:D,2,0) -> FEBP | B29: Changsha, Changsha, Hunan, China | C29: CY | D29: Shanghai, China | E29: GC; DG | G29: Shanghai, China | H29: 325 | I29: 550 | J29: 550 | K29: =IF(H29<>"",VLOOKUP($A29,$B$3:$E$10,2,FALSE)+H29,"--") -> 375 | L29: =IF(I29<>"",VLOOKUP($A29,$B$3:$E$10,3,FALSE)+I29,"--") -> 625 | M29: =IF(J29<>"",VLOOKUP($A29,$B$3:$E$10,4,FALSE)+J29,"--") -> 625
A30: =VLOOKUP(G30,LookupK!C:D,2,0) -> FEBP | B30: Changshu, Suzhou, Jiangsu, China | C30: CY | D30: Shanghai, China | E30: GC; DG | G30: Shanghai, China | H30: 175 | I30: 275 | J30: 275 | K30: =IF(H30<>"",VLOOKUP($A30,$B$3:$E$10,2,FALSE)+H30,"--") -> 225 | L30: =IF(I30<>"",VLOOKUP($A30,$B$3:$E$10,3,FALSE)+I30,"--") -> 350 | M30: =IF(J30<>"",VLOOKUP($A30,$B$3:$E$10,4,FALSE)+J30,"--") -> 350
A31: =VLOOKUP(G31,LookupK!C:D,2,0) -> FEBP | B31: Changzhou, Changzhou, Jiangsu, China | C31: CY | D31: Shanghai, China | E31: GC; DG | G31: Shanghai, China | H31: 175 | I31: 300 | J31: 300 | K31: =IF(H31<>"",VLOOKUP($A31,$B$3:$E$10,2,FALSE)+H31,"--") -> 225 | L31: =IF(I31<>"",VLOOKUP($A31,$B$3:$E$10,3,FALSE)+I31,"--") -> 375 | M31: =IF(J31<>"",VLOOKUP($A31,$B$3:$E$10,4,FALSE)+J31,"--") -> 375
A32: =VLOOKUP(G32,LookupK!C:D,2,0) -> FEBP | B32: Chengdu, Chengdu, Sichuan, China | C32: CY | D32: Shanghai, China | E32: GC; DG | G32: Shanghai, China | H32: 1250 | I32: 1600 | J32: 1600 | K32: =IF(H32<>"",VLOOKUP($A32,$B$3:$E$10,2,FALSE)+H32,"--") -> 1300 | L32: =IF(I32<>"",VLOOKUP($A32,$B$3:$E$10,3,FALSE)+I32,"--") -> 1675 | M32: =IF(J32<>"",VLOOKUP($A32,$B$3:$E$10,4,FALSE)+J32,"--") -> 1675
A33: =VLOOKUP(G33,LookupK!C:D,2,0) -> FEBP | B33: Chongqing, China | C33: CY | D33: Shanghai, China | E33: GC; DG | G33: Shanghai, China | H33: 400 | I33: 725 | J33: 725 | K33: =IF(H33<>"",VLOOKUP($A33,$B$3:$E$10,2,FALSE)+H33,"--") -> 450 | L33: =IF(I33<>"",VLOOKUP($A33,$B$3:$E$10,3,FALSE)+I33,"--") -> 800 | M33: =IF(J33<>"",VLOOKUP($A33,$B$3:$E$10,4,FALSE)+J33,"--") -> 800
... A120: =VLOOKUP(G120,LookupK!C:D,2,0) -> FEBP | B120: Zhuhai, Zhuhai, Guangdong, China | C120: CY | D120: Shekou, Shenzhen, Guangdong, China | E120: GC; DG | G120: Shekou, Shenzhen, Guangdong, China | H120: 225 | I120: 350 | J120: 350 | K120: =IF(H120<>"",VLOOKUP($A120,$B$3:$E$10,2,FALSE)+H120,"--") -> 275 | L120: =IF(I120<>"",VLOOKUP($A120,$B$3:$E$10,3,FALSE)+I120,"--") -> 425 | M120: =IF(J120<>"",VLOOKUP($A120,$B$3:$E$10,4,FALSE)+J120,"--") -> 425

Sheet Koper+Trieste
B3: Orient Overseas Container Line Ltd.
B4: =Introduction!D8 -> NEW: rate reference mentioned in your email
B5: =Introduction!B9 -> valid as from 01.12.2025 - 31.01.2026
B9: FAR EAST (direct calls) | C9: GATE IN subject to below + destination charges
B10: POL | C10: POD | D10: 20' GP | E10: 40' GP | F10: 40' HQ | G10: GC; DG
B11: Koper; Trieste | C11: Ningbo | D11: 50 | E11: 75 | F11: =E11 -> 75 | G11: DG; GC
B12: Koper; Trieste | C12: Port Klang | D12: =D11 -> 50 | E12: =E11 -> 75 | F12: =E12 -> 75 | G12: DG; GC
B13: Koper; Trieste | C13: Busan | D13: =D11 -> 50 | E13: =E11 -> 75 | F13: =E13 -> 75 | G13: DG; GC
B14: Koper; Trieste | C14: Shanghai | D14: =D11 -> 50 | E14: =E11 -> 75 | F14: =E14 -> 75 | G14: DG; GC
B15: Koper; Trieste | C15: Shekou | D15: =D11 -> 50 | E15: =E11 -> 75 | F15: =E15 -> 75 | G15: DG; GC
B16: Koper; Trieste | C16: Kaohsiung | D16: 100 | E16: 175 | F16: =E16 -> 175 | G16: DG; GC
B17: Koper; Trieste | C17: Hong Kong | D17: =D16 -> 100 | E17: =E16 -> 175 | F17: =E17 -> 175 | G17: DG; GC
B18: Koper; Trieste | C18: Qingdao | D18: =D17 -> 100 | E18: =E16 -> 175 | F18: =E18 -> 175 | G18: DG; GC
B19: Koper; Trieste | C19: Singapore | D19: =D17 -> 100 | E19: =E18 -> 175 | F19: =E19 -> 175 | G19: DG; GC
B20: Koper; Trieste | C20: Dalian | D20: =D17 -> 100 | E20: =E16 -> 175 | F20: =E20 -> 175 | G20: DG; GC
B21: Koper; Trieste | C21: Xingang | D21: =D17 -> 100 | E21: =E16 -> 175 | F21: =E21 -> 175 | G21: DG; GC
B23: Koper; Trieste | C23: Jeddah | D23: 550 | E23: 725 | F23: =E23 -> 725 | G23: DG; GC
B25: Australia / New Zealand (via Port Klang) | C25: GATE IN subject to below + destination charges
B26: POL | C26: POD | D26: 20' GP | E26: 40' GP | F26: 40' HQ | G26: GC; DG
B27: Koper; Trieste | C27: Adelaide | D27: 1005 | E27: 1505 | F27: 1505 | G27: DG; GC
B28: Koper; Trieste | C28: Fremantle | D28: 1005 | E28: 1505 | F28: 1505 | G28: DG; GC
B29: Koper; Trieste | C29: Brisbane | D29: 1005 | E29: 1505 | F29: 1505 | G29: DG; GC
B30: Koper; Trieste | C30: Melbourne | D30: 1005 | E30: 1505 | F30: 1505 | G30: DG; GC
B31: Koper; Trieste | C31: Sydney | D31: 1005 | E31: 1505 | F31: 1505 | G31: DG; GC
B32: Koper; Trieste | C32: Forrestfield (via Fremantle) | D32: =D27+305 -> 1310 | E32: =E27+405 -> 1910 | F32: =F27+405 -> 1910 | G32: DG; GC
B34: Koper; Trieste | C34: Auckland | D34: 1380 | E34: 1980 | F34: =E34 -> 1980 | G34: DG; GC
B35: Koper; Trieste | C35: Lyttelton | D35: 1380 | E35: =E34 -> 1980 | F35: =E35 -> 1980 | G35: DG; GC
B36: Koper; Trieste | C36: Tauranga | D36: 1380 | E36: =E34 -> 1980 | F36: =E36 -> 1980 | G36: DG; GC
B37: Koper; Trieste | C37: Napier | D37: 1380 | E37: =E34 -> 1980 | F37: =E37 -> 1980 | G37: DG; GC
B40: Far East Wing Ports | C40: GATE IN subject to below + destination charges
B41: POD | C41: via transshipment | D41: 20' GP | E41: 40' GP | F41: 40' HQ | G41: GC; DG
B42: Anji, Huzhou, Zhejiang, China | C42: Shanghai, China | D42: 225 | E42: 375 | F42: 375 | G42: GC; DG
B43: Anqing, Anqing, Anhui, China | C43: Shanghai, China | D43: 250 | E43: 375 | F43: 375 | G43: GC; DG
B44: Bangkok, Thailand | C44: Port Klang, Selangor, Malaysia | D44: 275 | E44: 425 | F44: 425 | G44: GC; DG
B45: Belawan, Sumatera Utara, Indonesia | C45: Port Klang, Selangor, Malaysia | D45: 350 | E45: 550 | F45: 550 | G45: GC; DG
B46: Bintulu, Sarawak, Malaysia | C46: Port Klang, Selangor, Malaysia | D46: 800 | E46: 1425 | F46: 1425 | G46: GC; DG
B47: Busan, South Korea | C47: Shanghai, China | D47: 95 | E47: 140 | F47: 140 | G47: GC; DG
B48: Changde, Changde, Hunan, China | C48: Shanghai, China | D48: 425 | E48: 775 | F48: 775 | G48: GC; DG
B49: Changsha, Changsha, Hunan, China | C49: Shanghai, China | D49: 375 | E49: 625 | F49: 625 | G49: GC; DG
B50: Changshu, Suzhou, Jiangsu, China | C50: Shanghai, China | D50: 225 | E50: 350 | F50: 350 | G50: GC; DG
B51: Changzhou, Changzhou, Jiangsu, China | C51: Shanghai, China | D51: 225 | E51: 375 | F51: 375 | G51: GC; DG
B52: Chengdu, Chengdu, Sichuan, China | C52: Shanghai, China | D52: 1300 | E52: 1675 | F52: 1675 | G52: GC; DG
B53: Chongqing, China | C53: Shanghai, China | D53: 450 | E53: 800 | F53: 800 | G53: GC; DG
... B64: Heshan, Jiangmen, Guangdong, China | C64: Shekou, Shenzhen, Guangdong, China | D64: 250 | E64: 375 | F64: 375 | G64: GC; DG
B65: Ho Chi Minh, Vietnam | C65: Port Klang, Selangor, Malaysia | D65: 200 | E65: 350 | F65: 350 | G65: GC; DG | H65: !! No DG acceptance in Cat Lai !!
B66: Hong Kong, Hong Kong, China | C66: Port Klang, Selangor, Malaysia | D66: 125 | E66: 150 | F66: 150 | G66: GC; DG
B67: Huadu, Guangzhou, Guangdong, China | C67: Shekou, Shenzhen, Guangdong, China | D67: 200 | E67: 325 | F67: 325 | G67: GC; DG
B68: Huangpu, Guangzhou, Guangdong, China | C68: Shekou, Shenzhen, Guangdong, China | D68: 250 | E68: 350 | F68: 350 | G68: GC; DG
B69: Huangshigang, Huangshi, Hubei, China | C69: Shanghai, China | D69: 250 | E69: 375 | F69: 375 | G69: GC; DG
B70: Jakarta, Indonesia | C70: Port Klang, Selangor, Malaysia | D70: 325 | E70: 475 | F70: 475 | G70: GC; DG
B71: Jiangmen, Jiangmen, Guangdong, China | C71: Shekou, Shenzhen, Guangdong, China | D71: 200 | E71: 300 | F71: 300 | G71: GC; DG
B72: Jiangyin, Wuxi, Jiangsu, China | C72: Shanghai, China | D72: 225 | E72: 375 | F72: 375 | G72: GC; DG
B73: Jiaoxin, Guangzhou, Guangdong, China | C73: Shekou, Shenzhen, Guangdong, China | D73: 200 | E73: 350 | F73: 350 | G73: GC; DG
B74: Jiaxing, Jiaxing, Zhejiang, China | C74: Shanghai, China | D74: 200 | E74: 325 | F74: 325 | G74: GC; DG
B75: Jingzhou, Jingzhou, Hubei, China | C75: Shanghai, China | D75: 375 | E75: 625 | F75: 625 | G75: GC; DG
B76: Jiujiang, Jiujiang, Jiangxi, China | C76: Shanghai, China | D76: 225 | E76: 300 | F76: 300 | G76: GC; DG
B77: Kota Kinabalu, Sabah, Malaysia | C77: Port Klang, Selangor, Malaysia | D77: 800 | E77: 1425 | F77: 1425 | G77: GC; DG
... B138: Zhuhai, Zhuhai, Guangdong, China | C138: Shekou, Shenzhen, Guangdong, China | D138: 275 | E138: 425 | F138: 425 | G138: GC; DG
B140: plus following surcharges, valid until further notice
B142: LSA Australia/New Zealand | C142: December USD 256,- per TEU // January USD 219,- per TEU - Low sulphur adjustment (floating)
B143: ETS Australia/New Zealand | C143: USD 21,- per TEU - Emission Trading System (floating)
B145: ISPS Koper: | C145: EUR 15 per Cont.
B146: LFN Trieste: | C146: EUR 20,- per Cont.
B147: AMS: | C147: USD 30,- per B/L - shipments to/via Japan/China/Israel
B148: DOC | C148: EUR 75,- per B/L (applies for non-Electronic Shipping Instruction only via My OOCL.com)
B149: MBF: | C149: EUR 40,- per booking (for non-Electronic Booking Instruction, except bookings to Russia until further notice)
B150: WRS (War Risk Surcharge) TRIESTE | C150: USD 50,- per TEU (except Jeddah) – War Risk Surcharge for Middle East Gulf region
B151: Status Change Fee | C151: EUR 90,- /Cntr in case of a difference between VGM declared on Container arrival at terminal and weight declared on loading list will exceed + / - 2 tons
B152: IMO: | C152: USD 100,- per CTR (dry) subject to PSA costs if transshipped via Singapore (subject to acceptance) ; except Malaysia
B153: IMO to/via Port Kelang: | C153: USD 150,-/200,-/200,- per 20’/40’/40’HQ DRY - subject to acceptance
B156: Please also note the new Demurrage/Detention Terms for Trieste and Koper
B157: https://www.oocl.com/slovenia/eng/localinformation/ddfreetime/Pages/default.aspx | D157: KOPER
B158: https://www.oocl.com/italy/eng/localinformation/ddfreetime/Pages/default.aspx | D158: TRIESTE
B160: RATE DATE IS SAILING DATE

Sheet Intra Europe
B3: Orient Overseas Container Line Ltd.
B4: =Introduction!D8 -> NEW: rate reference mentioned in your email
B5: =Introduction!B9 -> valid as from 01.12.2025 - 31.01.2026
B9: NET Turkey Service | D9: GATE IN subject to below + destination charges
B10: POL | C10: POD | D10: 20' Box | E10: 40' Box | F10: 40' HQ | G10: Loop
B11: HAM / BHV / ANR | C11: Istanbul (Kumport) | D11: 350 | E11: 250 | F11: =E11 -> 250 | G11: NET
B12: HAM / BHV / ANR | C12: Korfez (DP World Yarimca) | D12: =D11 -> 350 | E12: =E11 -> 250 | F12: =E12 -> 250 | G12: NET
B13: HAM / BHV / ANR | C13: Gemlik | D13: =D11 -> 350 | E13: =E11 -> 250 | F13: =E13 -> 250 | G13: NET
B14: HAM / BHV / ANR | C14: Aliaga (Izmir) | D14: =D13 -> 350 | E14: =E11 -> 250 | F14: =E14 -> 250 | G14: NET
B16: HAM / BHV / ANR | C16: Piraeus | D16: 485 | E16: 520 | F16: =E16 -> 520 | G16: NET
B17: RTM | C17: Piraeus | D17: 535 | E17: 695 | F17: =E17 -> 695 | G17: NET
B18: RTM | C18: Piraeus | D18: 450 | E18: 520 | F18: =E18 -> 520 | G18: NET2
B20: RTM / HAM / ANR | C20: Mersin | D20: 400 | E20: =F20 -> 450 | F20: 450 | G20: NET2
B21: RTM / HAM / ANR | C21: Iskenderun | D21: 450 | E21: 500 | F21: =E21 -> 500 | G21: NET2
B22: RTM / HAM / ANR | C22: El Dekheila | D22: 525 | E22: 650 | F22: =E22 -> 650 | G22: NET2
B24: HAM / RTM / ANR | C24: Ashdod (via Piraeus) | D24: 1100 | E24: 1300 | F24: =E24 -> 1300 | G24: NET; NET2
B25: HAM / RTM / ANR | C25: Haifa (via Piraeus) | D25: 1100 | E25: 1200 | F25: =E25 -> 1200 | G25: NET; NET2
B27: Included charges: BAF; LSA; THC
B28: -------------------------------------------
B29: plus following surcharges, valid until further notice
B31: ETS: | C31: December EUR 34,- per TEU // January EUR 53,- per TEU - Emission Trading System (floating)
B32: MBF: | C32: EUR 40,- per booking (for non-Electronic Booking Instruction, except bookings to Russia until further notice)
B33: AMS: | C33: USD 30,- per BL - shipments to/via Turkey & Egypt
B34: DOC: | C34: EUR 75,- per B/L (applies for non-Electronic Shipping Instruction only via My OOCL.com)
B35: WRP: | C35: USD 45,- per TEU War Risk Premium for all containers to and from Israel eff. 1st November 2024
B36: IMO | C36: EUR 150,-/150,-/150,- per 20’/40’/40’HQ DRY - subject to acceptance
B37: heavy weight add. | C37: EUR 100,- per 20' >= 21tons payload (except NET Loop)
B39: Plus origin charges (all listed on www.oocl.com/eng/resourcecenter/globalinfo/Pages/default.aspx )
B40: Plus destination charges (all listed on www.oocl.com/eng/resourcecenter/globalinfo/Pages/default.aspx )
B42: RATE DATE IS GATE IN DATE
B44: Freight prepaid only

Sheet Middle East
B3: Orient Overseas Container Line Ltd.
B4: =Introduction!D8 -> NEW: rate reference mentioned in your email
B5: =Introduction!B9 -> valid as from 01.12.2025 - 31.01.2026
F9: remark: no hazardous cargo on IP service!
B10: MIDDLE EAST (direct calls) | C10: GATE IN subject to below + destination charges
B11: POL | C11: POD | D11: 20' Box | E11: 40' Box | F11: 40' HQ | G11: GC;DG | H11: Loop
B12: HAM / RTM / ANR | C12: Jebel Ali, Dubai, United Arab Emirates | D12: 575 | E12: 575 | F12: =E12 -> 575 | G12: GC;DG | H12: IP1
B13: HAM / RTM / ANR | C13: Abu Dhabi, United Arab Emirates | D13: 575 | E13: 575 | F13: =E13 -> 575 | G13: GC;DG | H13: IP1
B15: MIDDLE EAST Wing Ports | C15: GATE IN subject to below + destination charges
B16: POD | C16: transshipment via | D16: 20' Box | E16: 40' Box | F16: 40' HQ | G16: GC;DG
B17: Ajman, United Arab Emirates | C17: Jebel Ali, Dubai, United Arab Emirates | D17: 875 | E17: 1025 | F17: 1025 | G17: GC;DG | H17: IP1
B18: Al Hidd, Muharraq Governorate, Bahrain | C18: Jebel Ali, Dubai, United Arab Emirates | D18: 825 | E18: 925 | F18: 925 | G18: GC;DG | H18: IP1
B19: Al Shuwaikh, Al Asamah, Kuwait | C19: Jebel Ali, Dubai, United Arab Emirates | D19: 900 | E19: 1150 | F19: 1150 | G19: GC;DG | H19: IP1
B20: Ar Riyad, Ar Riyad, Saudi Arabia | C20: Dammam, Ash Sharqiyah, Saudi Arabia | D20: 1175 | E20: 1575 | F20: 1575 | G20: GC;DG | H20: IP1
B21: Dammam, Ash Sharqiyah, Saudi Arabia | C21: Jebel Ali, Dubai, United Arab Emirates | D21: 925 | E21: 1125 | F21: 1125 | G21: GC;DG | H21: IP1
B22: Hamad port, Al Wakrah, Qatar | C22: Jebel Ali, Dubai, United Arab Emirates | D22: 950 | E22: 1050 | F22: 1050 | G22: GC;DG | H22: IP1
B23: Kuwait, Al Asamah, Kuwait | C23: Jebel Ali, Dubai, United Arab Emirates | D23: 900 | E23: 1150 | F23: 1150 | G23: GC;DG | H23: IP1
B24: Sharjah, United Arab Emirates | C24: Jebel Ali, Dubai, United Arab Emirates | D24: 725 | E24: 850 | F24: 850 | G24: GC;DG | H24: IP1
B25: Shuaiba, Al Ahmadi, Kuwait | C25: Jebel Ali, Dubai, United Arab Emirates | D25: 900 | E25: 1125 | F25: 1125 | G25: GC;DG | H25: IP1
B26: Sohar, Al Batinah North Governorate, Oman | C26: Jebel Ali, Dubai, United Arab Emirates | D26: 825 | E26: 925 | F26: 925 | G26: GC;DG | H26: IP1
B27: Umm Al Quwain, United Arab Emirates | C27: Jebel Ali, Dubai, United Arab Emirates | D27: 925 | E27: 1175 | F27: 1175 | G27: GC;DG | H27: IP1
B29: Included charges: BAF; CAF; CWX; CWC; EMS; ETS; GAS; LSA: SUZ; IFP; THC
B30: -------------------------------------------
B31: plus following surcharges, valid until further notice
B33: WRS (War Risk Surcharge): | C33: USD 50,- per TEU (except Jeddah)
B34: MBF: | C34: EUR 40,- per booking (for non-Electronic Booking Instruction, except bookings to Russia until further notice)
B35: DOC: | C35: EUR 75,- per B/L (applies for non-Electronic Shipping Instruction only via My OOCL.com)
B36: IMO: | C36: USD 75,- per CTR (dry) (subject to acceptance)
B38: Plus origin charges (all listed on www.oocl.com/eng/resourcecenter/globalinfo/Pages/default.aspx )
B39: Plus destination charges (all listed on www.oocl.com/eng/resourcecenter/globalinfo/Pages/default.aspx )
B41: RATE DATE IS SAILING DATE
B43: Freight prepaid only

Sheet Africa
B3: Orient Overseas Container Line Ltd.
B4: =Introduction!D8 -> NEW: rate reference mentioned in your email
B5: =Introduction!B9 -> valid as from 01.12.2025 - 31.01.2026
B9: EUR Payment!
B10: WEST AFRICA | C10: GATE IN subject to below + destination charges
B11: POL | C11: POD | D11: transshipment via | E11: 20' Box | F11: 40' Box | G11: 40' HQ | H11: GC;DG | I11: Loop
B12: HAM / RTM / ANR | C12: Abidjan (Ivory Coast) | D12: Algeciras | E12: 1075 | F12: 1550 | G12: =F12 -> 1550 | H12: GC;DG | I12: EEX; IP1
B13: HAM / RTM / ANR | C13: Apapa (Lagos - Nigeria)* | D13: Tema | E13: 2275 | F13: 2950 | G13: =F13 -> 2950 | H13: GC;DG | I13: EEX; IP1
B14: HAM / RTM / ANR | C14: Cotonou (Benin) | D14: Tema | E14: 1525 | F14: 1750 | G14: =F14 -> 1750 | H14: GC;DG | I14: EEX; IP1
B15: HAM / RTM / ANR | C15: Dakar (Senegal) | D15: Algeciras | E15: 1475 | F15: 1800 | G15: =F15 -> 1800 | H15: GC;DG | I15: EEX; IP1
B16: HAM / RTM / ANR | C16: Lekki (Nigeria) | D16: Tema | E16: 2275 | F16: 2950 | G16: =F16 -> 2950 | H16: GC;DG | I16: EEX; IP1
B17: HAM / RTM / ANR | C17: Lome (Togo) | D17: Tema | E17: 1525 | F17: 1750 | G17: =F17 -> 1750 | H17: GC;DG | I17: EEX; IP1
B18: HAM / RTM / ANR | C18: Tema (Ghana) | D18: Algeciras | E18: 1525 | F18: 1850 | G18: =F18 -> 1850 | H18: GC;DG | I18: EEX; IP1
B20: EUR Payment!
B21: EAST AFRICA | C21: GATE IN subject to below + destination charges
B22: POL | C22: POD | D22: transshipment via | E22: 20' Box | F22: 40' Box | G22: 40' HQ | H22: GC;DG | I22: Loop
B23: HAM / RTM / ANR | C23: Mombasa (Kenya) | D23: Jebel Ali | E23: 1775 | F23: 2200 | G23: =F23 -> 2200 | H23: GC | I23: IP1
B24: HAM / RTM / ANR | C24: Beira (Mozambique) | D24: Jebel Ali | E24: 1775 | F24: 2200 | G24: 2200 | H24: GC | I24: IP1
B25: HAM / RTM / ANR | C25: Maputo (Mozambique) | D25: Jebel Ali | E25: 1775 | F25: 2200 | G25: 2200 | H25: GC | I25: IP1
B26: HAM / RTM / ANR | C26: Dar Es Salaam (Tanzania) | D26: Jebel Ali | E26: 1775 | F26: 2200 | G26: 2200 | H26: GC | I26: IP1
H27: *remark: no hazardous cargo on IP service!
B29: Included charges: CWC; CWX; THC; EBS
B30: -------------------------------------------
B31: plus following surcharges, valid until further notice
B33: ETS: | C33: December EUR 6,- per TEU // January EUR 13,- per TEU - Emission Trading System (floating)
B34: LSA: | C34: December EUR 124,- per TEU // January EUR 116,- per TEU - Low sulphur adjustment (floating)
B35: *PSS | C35: EUR 980,- per Cont. for Lagos only
B36: MBF: | C36: EUR 40,- per booking (for non-Electronic Booking Instruction, except bookings to Russia until further notice)
B37: DOC: | C37: EUR 75,- per B/L (applies for non-Electronic Shipping Instruction only via My OOCL.com)
B38: IMO: | C38: EUR 200,- per TEU (dry) (subject to acceptance)
B40: Plus origin charges (all listed on www.oocl.com/eng/resourcecenter/globalinfo/Pages/default.aspx )
B41: Plus destination charges (all listed on www.oocl.com/eng/resourcecenter/globalinfo/Pages/default.aspx )
B43: RATE DATE IS SAILING DATE

Sheet India+Pakistan
B3: Orient Overseas Container Line Ltd.
B4: =Introduction!D8 -> NEW: rate reference mentioned in your email
B5: =Introduction!B9 -> valid as from 01.12.2025 - 31.01.2026
G8: remark: no hazardous cargo on IP service!
B9: INDIA / PAKISTAN | C9: GATE IN subject to below + destination charges
B10: POL | C10: POD | D10: 20' Box | E10: 40' Box | F10: 40' HQ | G10: GC;DG | H10: Loop
B11: HAM / RTM / ANR | C11: Nhava Sheva / Mundra (direct service) | D11: 550 | E11: 550 | F11: 550 | G11: GC | H11: IP1
B12: HAM / RTM / ANR | C12: Karachi (direct service) ** | D12: 800 | E12: 850 | F12: =E12 -> 850 | G12: GC | H12: IP1
B13: RTM / HAM / ANR | C13: Haldia (via Colombo) | D13: 1125 | E13: 1650 | F13: =E13 -> 1650 | G13: GC | H13: LL6
B14: RTM / HAM / ANR / WVN / ZEE | C14: Kolkata (via Port Klang / Singapore) | D14: =D13 -> 1125 | E14: =E13 -> 1650 | F14: =F13 -> 1650 | G14: GC | H14: LL1; LL5; LL6; LL7
B15: RTM / HAM / ANR | C15: Tuticorin (via Colombo) | D15: 650 | E15: 750 | F15: =E15 -> 750 | G15: GC | H15: LL6
B18: Far East direct calls & transshipments | C18: GATE IN GATE OUT subject to below + destination charges (all charges prepaid!)
B19: POL | C19: POD | D19: 20' Box | E19: 40' Box | F19: 40' HQ | G19: GC;DG | H19: Loop
B20: WVN / HAM / ZEE / RTM | C20: Chattogram (via Port Klang / Singapore / Colombo) | D20: 1300 | E20: 1600 | F20: 1600 | G20: GC;DG | H20: LL1; LL3; LL5; LL6; LL7
B21: HAM / RTM | C21: Colombo | D21: 550 | E21: 550 | F21: 550 | G21: GC;DG | H21: LL6
B23: ONCARRIAGE (ICD) | C23: REMARK: 18,00 % GST (Goods Service Tax) applicable on collect basis (vatos)
B24: harmless cargo ONLY!!!
B25: Pls see b.m. link:
B27: OOCL - Local Surcharges / Inland Haulage Tariff
B29: INDIA FREETIME
B30: 14 calendar days DET/DEM combined (2 in 1) free in port of discharge and ICD’s (excl port storage)
B31: OOCL - Demurrage & Detention Free Time and Charges
B34: Included charges: BAF; CAF; CWX; EMS; ETS; GAS; LSA: SUZ; IFP; THC
B35: -------------------------------------------
B36: plus following surcharges, valid until further notice
B38: MBF: | C38: EUR 40,- per booking (for non-Electronic Booking Instruction, except bookings to Russia until further notice)
B39: DOC: | C39: EUR 75,- per B/L (applies for non-Electronic Shipping Instruction only via My OOCL.com)
B40: IMO to Chattogram / Colombo on LL-services only: | C40: USD 100,- per CTR (dry) subject to PSA costs if transshipped via Singapore (subject to acceptance) ; except Malaysia
B41: *CWC applicable for Haldia/Kolkata only: | C41: USD 175,- per 20'GP >= 24 tons payload
B42: CLE Colombo (Cleaning Fee): | C42: USD 10,- per TEU prepaid
B43: CLE Chattogram (Cleaning Fee): | C43: BDT 500,- per CTR prepaid
B44: ** RES Karachi (Routing Emergency Surcharge) | C44: USD 200,- per CTR eff 6th May 2025
B46: Plus origin charges (all listed on www.oocl.com/eng/resourcecenter/globalinfo/Pages/default.aspx )
B47: Plus destination charges (all listed on www.oocl.com/eng/resourcecenter/globalinfo/Pages/default.aspx )
B49: PSA additionals
B50: Please note following PSA additional will be charged for transshipment via Singapore:
B52: PSA = DHT tariff per 20’/40’/45’ for DG t/s via SIN
B53: · PSA 3/2F/2S: SGD 180/360/405
B54: · PSA 2B/2C: SGD 930/1485/1643
B55: · PSA 2A: SGD 1080/1635/1793
B56: · PSA 1S: SGD 380/560/605
B57: · PSA 1C/1N: SGD 1130/1685/1843
B58: · PSA 1/1D: SGD 1490/2405/2653
B59: · PSA 2 (UN1057 only): SGD 1690/2605/2853
... B68: RATE DATE IS SAILING DATE

Sheet Australia & New Zealand
B3: Orient Overseas Container Line Ltd.
B4: =Introduction!D8 -> NEW: rate reference mentioned in your email
B5: =Introduction!B9 -> valid as from 01.12.2025 - 31.01.2026
B9: AUSTRALIA | D9: GATE IN subject to below + destination charges
B10: POL | C10: POD | D10: Transshipment via | E10: 20' Box | F10: 40' Box | G10: 40' HQ
B11: WVN / HAM / RTM / ANR / ZEE | C11: Sydney | D11: Singapore / Port Klang | E11: 800 | F11: 1300 | G11: 1300
B12: WVN / HAM / RTM / ANR / ZEE | C12: Melbourne | D12: Singapore / Port Klang | E12: =E13 -> 800 | F12: =F11 -> 1300 | G12: =F12 -> 1300
B13: WVN / HAM / RTM / ANR / ZEE | C13: Brisbane | D13: Singapore / Port Klang | E13: =E11 -> 800 | F13: =F11 -> 1300 | G13: =F13 -> 1300
B14: WVN / HAM / RTM / ANR / ZEE | C14: Fremantle | D14: Singapore / Port Klang | E14: =E13 -> 800 | F14: =F11 -> 1300 | G14: =F14 -> 1300
B15: WVN / HAM / RTM / ANR / ZEE | C15: Adelaide | D15: Singapore / Port Klang | E15: =E14 -> 800 | F15: =F11 -> 1300 | G15: =F15 -> 1300
B16: WVN / HAM / RTM / ANR / ZEE | C16: Devonport | D16: via Singapore/Port Klang-Melbourne | E16: 2430 | F16: 3725 | G16: =F16 -> 3725
B17: WVN / HAM / RTM / ANR / ZEE | C17: Forrestfield | D17: via Fremantle | E17: =E15+305 -> 1105 | F17: =F15+405 -> 1705 | G17: =F17 -> 1705
B19: NEW ZEALAND | D19: GATE IN subject to below + destination charges
B20: POL | C20: POD | D20: Transshipment via | E20: 20' Box | F20: 40' Box | G20: 40' HQ
B21: WVN / HAM / RTM / ANR / ZEE | C21: Auckland | D21: Singapore / Port Klang | E21: 1150 | F21: 1500 | G21: =F21 -> 1500
B22: WVN / HAM / RTM / ANR / ZEE | C22: Lyttelton | D22: Singapore / Port Klang | E22: =E21 -> 1150 | F22: =F21 -> 1500 | G22: =F22 -> 1500
B23: WVN / HAM / RTM / ANR / ZEE | C23: Tauranga | D23: Singapore / Port Klang | E23: =E21 -> 1150 | F23: =F21 -> 1500 | G23: =F23 -> 1500
B24: WVN / HAM / RTM / ANR / ZEE | C24: Napier | D24: Singapore / Port Klang | E24: =E21 -> 1150 | F24: =F21 -> 1500 | G24: =F24 -> 1500
B25: WVN / HAM / RTM / ANR / ZEE | C25: Wellington | D25: Singapore / Port Klang | E25: =E21 -> 1150 | F25: =F21 -> 1500 | G25: =F25 -> 1500
B27: Included charges: BAF; CAF; CWC; CWX; EMS: GAS; SUZ; THC; IFP
B28: -------------------------------------------
B29: plus following surcharges, valid until further notice
B31: ETS: | C31: December USD 35,- per TEU // January USD 51,- per TEU - Emission Trading System (floating)
B32: LSA: | C32: December USD 237,- per TEU // January USD 213,- per TEU - Low sulphur adjustment (floating)
B33: MBF: | C33: EUR 40,- per booking (for non-Electronic Booking Instruction, except bookings to Russia until further notice)
B34: DOC: | C34: EUR 75,- per B/L (applies for non-Electronic Shipping Instruction only via My OOCL.com)
B35: AMS: | C35: EUR 25,- per B/L - shipments to/via Japan/China/Israel
B36: IMO: | C36: USD 150,-/200,-/200,- per 20’/40’/40’HQ (dry) – subject to PSA costs when transshipped via Singapore (subject to acceptance)
B38: Plus origin charges (all listed on www.oocl.com/eng/resourcecenter/globalinfo/Pages/default.aspx )
B39: Plus destination charges (all listed on www.oocl.com/eng/resourcecenter/globalinfo/Pages/default.aspx )
B41: For your PSA Group (to/via Singapore) please check with local OOCL Customer Service
B43: PSA costs = DHT tariff per 20’/40’/45’ for DG t/s via SIN valid till 31.01.2026
B44: · PSA 3/2F/2S: SGD 180/360/405
B45: · PSA 2B/2C: SGD 930/1485/1643
B46: · PSA 2A: SGD 1080/1635/1793
B47: · PSA 1S: SGD 380/560/605
B48: · PSA 1C/1N: SGD 1130/1685/1843
B49: · PSA 1/1D: SGD 1490/2405/2653
B50: · PSA 2 (UN1057 only): SGD 1690/2605/2853
B51: · PSA 2 (except UN1057): SGD 1290/2205/2453
B54: PSA costs = DHT tariff per 20’/40’/45’ for DG t/s via SIN as from 01.02.2026
B55: PSA Dangerous Good Group | C55: per 20/40' CTR
B56: 3/2F/2S | C56: USD 140/280
B57: 2B/2S | C57: USD 730/1160
B58: 2A | C58: USD 850/1280
B59: 1S | C59: USD 305/445
B60: 1C/1N | C60: USD 890/1320
B61: 2 - lighter UN1057 | C61: USD 1325/2030
B62: 2 - except for lighter UN1057 | C62: USD 1010/1720
B63: 1/1D | C63: USD 1165/1875
B65: DG via Port Klang:
B66: Please check the acceptance of dangerous goods for transshipment in Port Kelang.
B68: RATE DATE IS SAILING DATE
B70: Freight prepaid only

Sheet Special Equipment
G4: Type | H4: max. length in gauge | I4: max. width in gauge | J4: max. height in gauge | K4: max. top loading width | L4: max. payload
G5: 20' OT | H5: 589 cm | I5: 235 cm | J5: 234 cm | K5: 220 cm | L5: 28.000 kos
G6: 40' OT | H6: 1203 cm | I6: 235 cm | J6: 234 cm | K6: 220 cm | L6: 26.500 kos
G7: 40' OQ | H7: 1203 cm | I7: 235 cm | J7: 265 cm | K7: 220 cm | L7: 26.500 kos | M7: OQ = Open Top High Cube
G8: 40'OQ max. cargo height = 247 cm if cargo width is >= 223 cm
G9: 20' FR | H9: 550 cm | I9: 244 cm | J9: 220 cm | K9: - | L9: 31.000 kos
G10: 40' FR | H10: 1150 cm* | I10: 244 cm | J10: 195 cm | K10: - | L10: 39.600 kos
G11: 40' FQ | H11: 1150 cm * | I11: 244 cm | J11: 226 cm | K11: - | L11: 47.300 kos | M11: FQ = Flat High Cube
G12: max. cargo width / height: 395 cm
G13: * if OW / OWOH
I15: Europe - Far East Ratesheet
I16: Service Contract Number: FE140000
E17: valid as from 01.01.2026 - 31.01.2026
X20: Restrictions
B21: POD | C21: POL | D21: T/S | E21: 20' OT/FR IG | F21: 20' OT/FR OH | G21: 20' FR(OW) | H21: 20' FR OH OW one side | I21: 20' FR OWOH | J21: 40' OT IG | K21: 40OQ IG | L21: 40' FR IG | M21: 40FQ IG | N21: 40' OT OH | O21: 40' OQ OH | P21: 40' FR OH | Q21: 40' FQ OH | R21: 40' FR OW | S21: 40' FQ OW | T21: 40' FR OH OW one side | U21: 40' FQ OH OW one side | V21: 40' FR OWOH | W21: 40' FQ OWOH | X21: Max payload / to | Y21: Max OW / cm (per side) | Z21: Max OH / cm
B23: Main Ports | C23: GATE IN + AMS / DOC fee where applicable + destination charges
B24: Dalian | C24: HAM / RTM / ANR | D24: direct | E24: 250 | F24: 750 | G24: 1050 | H24: 1450 | I24: 1550 | J24: 450 | K24: 550 | L24: 450 | M24: 550 | N24: 875 | O24: 975 | P24: 875 | Q24: 975 | R24: 1125 | S24: 1275 | T24: 1475 | U24: 1575 | V24: 1650 | W24: 1750 | X24: 34**
B25: Hong Kong | C25: HAM / RTM / ZEE | D25: direct | E25: 250 | F25: 750 | G25: 1050 | H25: 1450 | I25: 1550 | J25: 450 | K25: 550 | L25: 450 | M25: 550 | N25: 875 | O25: 975 | P25: 875 | Q25: 975 | R25: 1125 | S25: 1275 | T25: 1475 | U25: 1575 | V25: 1650 | W25: 1750 | X25: 34**
B26: Kaohsiung | C26: HAM / RTM | D26: direct | E26: 250 | F26: 750 | G26: 1050 | H26: 1450 | I26: 1550 | J26: 450 | K26: 550 | L26: 450 | M26: 550 | N26: 875 | O26: 975 | P26: 875 | Q26: 975 | R26: 1125 | S26: 1275 | T26: 1475 | U26: 1575 | V26: 1650 | W26: 1750 | X26: 34**
B27: Ningbo | C27: WVN / HAM / RTM / ANR / ZEE | D27: direct | E27: 250 | F27: 750 | G27: 1050 | H27: 1450 | I27: 1550 | J27: 450 | K27: 550 | L27: 450 | M27: 550 | N27: 875 | O27: 975 | P27: 875 | Q27: 975 | R27: 1125 | S27: 1275 | T27: 1475 | U27: 1575 | V27: 1650 | W27: 1750 | X27: 34**
B28: Port Klang | C28: HAM / RTM / ANR / ZEE | D28: direct | E28: 250 | F28: 750 | G28: 1050 | H28: 1450 | I28: 1550 | J28: 450 | K28: 550 | L28: 450 | M28: 550 | N28: 875 | O28: 975 | P28: 875 | Q28: 975 | R28: 1125 | S28: 1275 | T28: 1475 | U28: 1575 | V28: 1650 | W28: 1750 | X28: 34**
B29: Qingdao | C29: HAM / RTM / ANR / WVN / ZEE | D29: direct | E29: 250 | F29: 750 | G29: 1050 | H29: 1450 | I29: 1550 | J29: 450 | K29: 550 | L29: 450 | M29: 550 | N29: 875 | O29: 975 | P29: 875 | Q29: 975 | R29: 1125 | S29: 1275 | T29: 1475 | U29: 1575 | V29: 1650 | W29: 1750 | X29: 34**
B30: Shanghai | C30: WVN / HAM / RTM / ANR / ZEE | D30: direct | E30: 250 | F30: 750 | G30: 1050 | H30: 1450 | I30: 1550 | J30: 450 | K30: 550 | L30: 450 | M30: 550 | N30: 875 | O30: 975 | P30: 875 | Q30: 975 | R30: 1125 | S30: 1275 | T30: 1475 | U30: 1575 | V30: 1650 | W30: 1750 | X30: 34**
B31: Singapore | C31: ZEE / WVN /HAM / RTM /ANR | D31: direct | E31: 250 | F31: 750 | G31: 1050 | H31: 1450 | I31: 1550 | J31: 450 | K31: 550 | L31: 450 | M31: 550 | N31: 875 | O31: 975 | P31: 875 | Q31: 975 | R31: 1125 | S31: 1275 | T31: 1475 | U31: 1575 | V31: 1650 | W31: 1750 | X31: 34**
B32: Taipeh | C32: HAM / RTM | D32: direct | E32: 250 | F32: 750 | G32: 1050 | H32: 1450 | I32: 1550 | J32: 450 | K32: 550 | L32: 450 | M32: 550 | N32: 875 | O32: 975 | P32: 875 | Q32: 975 | R32: 1125 | S32: 1275 | T32: 1475 | U32: 1575 | V32: 1650 | W32: 1750 | X32: 34**
B33: Xingang | C33: HAM / RTM / ANR | D33: direct | E33: 250 | F33: 750 | G33: 1050 | H33: 1450 | I33: 1550 | J33: 450 | K33: 550 | L33: 450 | M33: 550 | N33: 875 | O33: 975 | P33: 875 | Q33: 975 | R33: 1125 | S33: 1275 | T33: 1475 | U33: 1575 | V33: 1650 | W33: 1750 | X33: 34**
B34: Xiamen | C34: WVN / HAM / RTM / ZEE | D34: direct | E34: 250 | F34: 750 | G34: 1050 | H34: 1450 | I34: 1550 | J34: 450 | K34: 550 | L34: 450 | M34: 550 | N34: 875 | O34: 975 | P34: 875 | Q34: 975 | R34: 1125 | S34: 1275 | T34: 1475 | U34: 1575 | V34: 1650 | W34: 1750 | X34: 34**
B35: Yantian | C35: HAM / RTM / ZEE / WVN | D35: direct | E35: 250 | F35: 750 | G35: 1050 | H35: 1450 | I35: 1550 | J35: 450 | K35: 550 | L35: 450 | M35: 550 | N35: 875 | O35: 975 | P35: 875 | Q35: 975 | R35: 1125 | S35: 1275 | T35: 1475 | U35: 1575 | V35: 1650 | W35: 1750 | X35: 34**
B36: Kobe / Nagoya /Tokyo / Yokohama / Osaka* | C36: HAM / RTM / ANR | D36: Port Klang | E36: 1100 | F36: 1700 | G36: 2300 | H36: 2650 | I36: 2850 | J36: 1425 | K36: 1525 | L36: 1425 | M36: 1525 | N36: 2125 | O36: 2225 | P36: 2125 | Q36: 2225 | R36: 2475 | S36: 2575 | T36: 3225 | U36: 3325 | V36: 3600 | W36: 3700 | X36: 29** | Y36: 20 | Z36: 180
B37: Kobe / Nagoya /Tokyo / Yokohama / Osaka* | C37: HAM / RTM / ANR | D37: Port Klang | E37: 1100 | F37: 2150 | G37: 2750 | H37: 3100 | I37: 3300 | J37: 1425 | K37: 1525 | L37: 1425 | M37: 1525 | N37: 2575 | O37: 2675 | P37: 2575 | Q37: 2675 | R37: 2925 | S37: 3025 | T37: 3675 | U37: 3775 | V37: 4050 | W37: 4150 | X37: 29** | Z37: 200
B38: Colombo (gigo all in incl. THD) | C38: HAM / RTM | D38: direct | E38: 250 | F38: 750 | G38: 1050 | H38: 1650 | I38: 1550 | J38: 450 | K38: 550 | L38: 450 | M38: 550 | N38: 875 | O38: 975 | P38: 875 | Q38: 975 | R38: 1125 | S38: 1275 | T38: 1775 | U38: 1875 | V38: 1650 | W38: 1750 | X38: 34**
B39: *direct delivery is a must for OOG at JAPAN | X39: **weight above on request!
B41: Australia Main Ports | C41: GATE IN + ETS / LSA / AMS / DOC fee where applicable + destination charges
B42: Brisbane / Sydney / Melbourne / Fremantle / Adelaide | C42: HAM / RTM / ANR | D42: Port Klang | E42: 1300 | F42: on request | G42: on request | H42: on request | I42: on request | J42: 2150 | K42: 2250 | L42: 2150 | M42: 2250 | N42: on request | O42: on request | P42: on request | Q42: on request | R42: on request | S42: on request | T42: on request | U42: on request | V42: on request | W42: on request | X42: 34 | Y42: 10 | Z42: 176
B43: Brisbane / Sydney / Melbourne / Fremantle / Adelaide | C43: WVN / ZEE | D43: Singapore | E43: 1300 | F43: on request | G43: on request | H43: on request | I43: on request | J43: 2150 | K43: 2250 | L43: 2150 | M43: 2250 | N43: on request | O43: on request | P43: on request | Q43: on request | R43: on request | S43: on request | T43: on request | U43: on request | V43: on request | W43: on request | X43: 34 | Y43: 10 | Z43: 176
B44: direct delivery is a must for OOG at Australia
B46: New Zealand Main Ports | C46: GATE IN + ETS / LSA / AMS / DOC fee where applicable + destination charges
B47: Auckland / Lyttelton | C47: HAM / RTM / ANR | D47: Port Klang | E47: 1600 | F47: n.a. | G47: n.a. | H47: n.a. | I47: n.a. | J47: 2450 | K47: 2550 | L47: 2450 | M47: 2550 | N47: n.a. | O47: n.a. | P47: n.a. | Q47: n.a. | R47: n.a. | S47: n.a. | T47: n.a. | U47: n.a. | V47: n.a. | W47: n.a. | X47: 34 | Y47: IG only | Z47: IG only
B48: Auckland / Lyttelton | C48: ZEE / WVN | D48: Singapore | E48: 1600 | F48: n.a. | G48: n.a. | H48: n.a. | I48: n.a. | J48: 2450 | K48: 2550 | L48: 2450 | M48: 2550 | N48: n.a. | O48: n.a. | P48: n.a. | Q48: n.a. | R48: n.a. | S48: n.a. | T48: n.a. | U48: n.a. | V48: n.a. | W48: n.a. | X48: 34 | Y48: IG only | Z48: IG only
B49: Tauranga / Napier / Wellington | C49: HAM / RTM / ANR | D49: Port Klang | E49: 1600 | F49: n.a. | G49: n.a. | H49: n.a. | I49: n.a. | J49: 2450 | K49: 2550 | L49: 2450 | M49: 2550 | N49: n.a. | O49: n.a. | P49: n.a. | Q49: n.a. | R49: n.a. | S49: n.a. | T49: n.a. | U49: n.a. | V49: n.a. | W49: n.a. | X49: 34 | Y49: IG only | Z49: IG only
B51: India Main Ports * | C51: GATE IN + AMS / DOC fee where applicable + destination charges
B52: Nhava Sheva / Mundra | C52: HAM /RTM / ANR | D52: direct (IP1) | E52: 1150 | F52: 2150 | G52: n.a. | H52: n.a. | I52: n.a. | J52: 1175 | K52: 1275 | L52: 1175 | M52: 1275 | N52: 2550 | O52: 2650 | P52: 2550 | Q52: 2650 | R52: n.a. | S52: n.a. | T52: n.a. | U52: n.a. | V52: n.a. | W52: n.a. | X52: 34
B53: no hazardous cargo on IP service!
B56: Middle East Ports * | C56: GATE IN + AMS / DOC fee where applicable + destination charges
B57: Jebel Ali | C57: HAM /RTM / ANR | D57: direct (IP1) | E57: 1150 | F57: 2150 | G57: n.a. | H57: n.a. | I57: n.a. | J57: 1175 | K57: 1275 | L57: 1175 | M57: 1275 | N57: 2550 | O57: 2650 | P57: 2550 | Q57: 2650 | R57: n.a. | S57: n.a. | T57: n.a. | U57: n.a. | V57: n.a. | W57: n.a. | X57: 34 | Y57: 80 | Z57: 200
B58: Abu Dhabi | C58: HAM /RTM / ANR | D58: direct (IP1) | E58: 1425 | F58: n.a. | G58: n.a. | H58: n.a. | I58: n.a. | J58: 1625 | K58: 1725 | L58: 1625 | M58: 1725 | N58: n.a. | O58: n.a. | P58: n.a. | Q58: n.a. | R58: n.a. | S58: n.a. | T58: n.a. | U58: n.a. | V58: n.a. | W58: n.a. | X58: 34 | Y58: 80 | Z58: 200
B59: Al Hidd | C59: HAM /RTM / ANR | D59: Jebel Ali | E59: 1400 | F59: n.a. | G59: n.a. | H59: n.a. | I59: n.a. | J59: 1525 | K59: 1625 | L59: 1525 | M59: 1625 | N59: n.a. | O59: n.a. | P59: n.a. | Q59: n.a. | R59: n.a. | S59: n.a. | T59: n.a. | U59: n.a. | V59: n.a. | W59: n.a. | X59: 34 | Y59: 80 | Z59: 200
B60: Dammam | C60: HAM /RTM / ANR | D60: Jebel Ali | E60: 1250 | F60: n.a. | G60: n.a. | H60: n.a. | I60: n.a. | J60: 1325 | K60: 1425 | L60: 1325 | M60: 1425 | N60: n.a. | O60: n.a. | P60: n.a. | Q60: n.a. | R60: n.a. | S60: n.a. | T60: n.a. | U60: n.a. | V60: n.a. | W60: n.a. | X60: 34 | Y60: 80 | Z60: 200
B61: Al Shuwaikh | C61: HAM /RTM / ANR | D61: Jebel Ali | E61: 1400 | F61: n.a. | G61: n.a. | H61: n.a. | I61: n.a. | J61: 1575 | K61: 1675 | L61: 1575 | M61: 1675 | N61: n.a. | O61: n.a. | P61: n.a. | Q61: n.a. | R61: n.a. | S61: n.a. | T61: n.a. | U61: n.a. | V61: n.a. | W61: n.a. | X61: 34 | Y61: 80 | Z61: 200
B62: Shuaiba | C62: HAM /RTM / ANR | D62: Jebel Ali | E62: 1400 | F62: n.a. | G62: n.a. | H62: n.a. | I62: n.a. | J62: 1575 | K62: 1675 | L62: 1575 | M62: 1675 | N62: n.a. | O62: n.a. | P62: n.a. | Q62: n.a. | R62: n.a. | S62: n.a. | T62: n.a. | U62: n.a. | V62: n.a. | W62: n.a. | X62: 34 | Y62: 80 | Z62: 200
B63: Sohar | C63: HAM /RTM / ANR | D63: Jebel Ali | E63: 1300 | F63: n.a. | G63: n.a. | H63: n.a. | I63: n.a. | J63: 1375 | K63: 1475 | L63: 1375 | M63: 1475 | N63: n.a. | O63: n.a. | P63: n.a. | Q63: n.a. | R63: n.a. | S63: n.a. | T63: n.a. | U63: n.a. | V63: n.a. | W63: n.a. | X63: 34 | Y63: 80 | Z63: 200
B64: Sharjah | C64: HAM /RTM / ANR | D64: Jebel Ali | E64: 1450 | F64: n.a. | G64: n.a. | H64: n.a. | I64: n.a. | J64: 1575 | K64: 1675 | L64: 1575 | M64: 1675 | N64: n.a. | O64: n.a. | P64: n.a. | Q64: n.a. | R64: n.a. | S64: n.a. | T64: n.a. | U64: n.a. | V64: n.a. | W64: n.a. | X64: 34 | Y64: 80 | Z64: 200
B65: Umm Qasr | C65: HAM /RTM / ANR | D65: Jebel Ali | E65: 1550 | F65: n.a. | G65: n.a. | H65: n.a. | I65: n.a. | J65: 1675 | K65: 1775 | L65: 1675 | M65: 1775 | N65: n.a. | O65: n.a. | P65: n.a. | Q65: n.a. | R65: n.a. | S65: n.a. | T65: n.a. | U65: n.a. | V65: n.a. | W65: n.a. | X65: 34 | Y65: 80 | Z65: 200
B66: no hazardous cargo on IP service!
B69: South East Asia Wing Ports | C69: GATE IN + AMS / DOC fee where applicable + destination charges
B70: Jakarta | C70: ZEE / WVN / HAM / RTM/ ANR | D70: Singapore | E70: 600 | F70: 2600 | G70: 2950 | H70: 3350 | I70: 3450 | J70: 1100 | K70: 1200 | L70: 1100 | M70: 1200 | N70: 3275 | O70: 3375 | P70: 3275 | Q70: 3375 | R70: 3575 | S70: 3675 | T70: 3925 | U70: 4025 | V70: 4250 | W70: 4450 | X70: 29 | Y70: 80 | Z70: 200
E71: 600 | F71: 1800 | G71: 2150 | H71: 2550 | I71: 2650 | J71: 1100 | K71: 1200 | L71: 1100 | M71: 1200 | N71: 2475 | O71: 2575 | P71: 2475 | Q71: 2575 | R71: 2775 | S71: 2875 | T71: 3125 | U71: 3225 | V71: 3450 | W71: 3550 | X71: 29 | Y71: 20 | Z71: 120
B72: Jakarta | C72: HAM / RTM / ANR | D72: Port Klang | E72: 600 | F72: 2600 | G72: 2950 | H72: 3350 | I72: 3450 | J72: 1100 | K72: 1200 | L72: 1100 | M72: 1200 | N72: 3275 | O72: 3375 | P72: 3275 | Q72: 3375 | R72: 3575 | S72: 3675 | T72: 3925 | U72: 4025 | V72: 4150 | W72: 4250 | X72: 29 | Y72: 80 | Z72: 200
B73: Keelung | C73: HAM/RTM | D73: Kaohsiung | E73: 1250 | F73: n.a. | G73: n.a. | H73: n.a. | I73: n.a. | J73: 1525 | K73: 1625 | L73: 1525 | M73: 1625 | N73: n.a. | O73: n.a. | P73: n.a. | Q73: n.a. | R73: n.a. | S73: n.a. | T73: n.a. | U73: n.a. | V73: n.a. | W73: n.a. | X73: 20
E74: 1500 | F74: n.a. | G74: n.a. | H74: n.a. | I74: n.a. | J74: 1775 | K74: 1875 | L74: 1775 | M74: 1875 | N74: n.a. | O74: n.a. | P74: n.a. | Q74: n.a. | R74: n.a. | S74: n.a. | T74: n.a. | U74: n.a. | V74: n.a. | W74: n.a. | X74: 26
B75: Taichung | C75: HAM/RTM | D75: Kaohsiung | E75: 950 | F75: n.a. | G75: n.a. | H75: n.a. | I75: n.a. | J75: 1075 | K75: 1175 | L75: 1075 | M75: 1175 | N75: n.a. | O75: n.a. | P75: n.a. | Q75: n.a. | R75: n.a. | S75: n.a. | T75: n.a. | U75: n.a. | V75: n.a. | W75: n.a. | X75: 20
E76: 1250 | F76: n.a. | G76: n.a. | H76: n.a. | I76: n.a. | J76: 1325 | K76: 1425 | L76: 1325 | M76: 1425 | N76: n.a. | O76: n.a. | P76: n.a. | Q76: n.a. | R76: n.a. | S76: n.a. | T76: n.a. | U76: n.a. | V76: n.a. | W76: n.a. | X76: 26
B77: Semarang | C77: ZEE / WVN / HAM / RTM / ANR | D77: Singapore | E77: 750 | F77: 2550 | G77: 3150 | H77: 3400 | I77: 3600 | J77: 1275 | K77: 1375 | L77: 1275 | M77: 1375 | N77: 3225 | O77: 3325 | P77: 3225 | Q77: 3325 | R77: 3475 | S77: 3575 | T77: 3925 | U77: 4025 | V77: 4300 | W77: 4400 | X77: 29 | Y77: 78 | Z77: 134
E78: 750 | F78: 1750 | G78: 2350 | H78: 2600 | I78: 2800 | J78: 1275 | K78: 1375 | L78: 1275 | M78: 1375 | N78: 2425 | O78: 2525 | P78: 2425 | Q78: 2525 | R78: 2675 | S78: 2775 | T78: 3125 | U78: 3225 | V78: 3500 | W78: 3600 | X78: 29 | Y78: 20 | Z78: 120
C79: HAM / RTM / ANR | D79: Port Klang | E79: 600 | F79: 1600 | G79: 3200 | H79: 3450 | I79: 3700 | J79: 1075 | K79: 1175 | L79: 1075 | M79: 1175 | N79: 2175 | O79: 2275 | P79: 2175 | Q79: 2275 | R79: 2425 | S79: 2525 | T79: 2925 | U79: 3025 | V79: 3350 | W79: 3450 | X79: 29 | Y79: 78 | Z79: 134
B80: Surabaya | C80: ZEE / WVN / HAM / RTM / ANR | D80: Singapore | E80: 750 | F80: 2550 | G80: 3150 | H80: 3400 | I80: 3600 | J80: 1275 | K80: 1375 | L80: 1275 | M80: 1375 | N80: 3225 | O80: 3325 | P80: 3225 | Q80: 3325 | R80: 3475 | S80: 3575 | T80: 3925 | U80: 4025 | V80: 4300 | W80: 4400 | X80: 29 | Y80: 80 | Z80: 200
E81: 750 | F81: 1750 | G81: 2350 | H81: 2600 | I81: 2800 | J81: 1275 | K81: 1375 | L81: 1275 | M81: 1375 | N81: 2425 | O81: 2525 | P81: 2425 | Q81: 2525 | R81: 2675 | S81: 2775 | T81: 3125 | U81: 3225 | V81: 3500 | W81: 3600 | X81: 29 | Y81: 20 | Z81: 120
B82: Belawan | C82: ZEE / WVN / HAM / RTM / ANR | D82: Singapore | E82: 750 | F82: 2550 | G82: 3150 | H82: 3400 | I82: 3600 | J82: 1275 | K82: 1375 | L82: 1275 | M82: 1375 | N82: 3225 | O82: 3325 | P82: 3225 | Q82: 3325 | R82: 3475 | S82: 3575 | T82: 3925 | U82: 4025 | V82: 4300 | W82: 4400 | X82: 26
E83: 750 | F83: 1750 | G83: 2350 | H83: 2600 | I83: 2800 | J83: 1275 | K83: 1375 | L83: 1275 | M83: 1375 | N83: 2425 | O83: 2525 | P83: 2425 | Q83: 2525 | R83: 2675 | S83: 2775 | T83: 3125 | U83: 3225 | V83: 3500 | W83: 3600 | X83: 26 | Y83: 15 | Z83: 120
C84: HAM / RTM / ANR | D84: Port Klang | E84: 600 | F84: 1600 | G84: 3200 | H84: 3450 | I84: 3700 | J84: 1075 | K84: 1175 | L84: 1075 | M84: 1175 | N84: 2175 | O84: 2275 | P84: 2175 | Q84: 2275 | R84: 2425 | S84: 2525 | T84: 2925 | U84: 3025 | V84: 3350 | W84: 3450 | X84: 26
B85: Pasir Gudang | C85: ZEE/ WVN / HAM / RTM / ANR | D85: Singapore | E85: 850 | F85: 2050 | G85: 2700 | H85: 3150 | I85: 3350 | J85: 1075 | K85: 1175 | L85: 1075 | M85: 1175 | N85: 2425 | O85: 2525 | P85: 2425 | Q85: 2525 | R85: 2725 | S85: 2825 | T85: 3075 | U85: 3175 | V85: 3835 | W85: 3935 | X85: 29 | Y85: 80 | Z85: 200
B86: Penang | C86: HAM / RTM / ANR | D86: Port Klang | E86: 950 | F86: 1750 | G86: 2500 | H86: 2950 | I86: 3150 | J86: 1225 | K86: 1325 | L86: 1225 | M86: 1325 | N86: 2075 | O86: 2175 | P86: 2075 | Q86: 2175 | R86: 2475 | S86: 2575 | T86: 3325 | U86: 3425 | V86: 3700 | W86: 3800 | X86: 29 | Y86: 80 | Z86: 200
B87: Penang | C87: ZEE/ WVN / HAM / RTM / ANR | D87: Singapore | E87: 1000 | F87: 1850 | G87: 2600 | H87: 3050 | I87: 3250 | J87: 1275 | K87: 1375 | L87: 1275 | M87: 1375 | N87: 2175 | O87: 2275 | P87: 2175 | Q87: 2275 | R87: 2575 | S87: 2675 | T87: 3425 | U87: 3525 | V87: 3800 | W87: 3900 | X87: 29 | Y87: 80 | Z87: 200
B88: Laem Chabang | C88: ZEE / WVN / HAM / RTM / ANR | D88: Singapore | E88: 900 | F88: 2500 | G88: 3150 | H88: 3350 | I88: 3600 | J88: 1275 | K88: 1325 | L88: 1275 | M88: 1325 | N88: 2825 | O88: 2925 | P88: 2825 | Q88: 2925 | R88: 3225 | S88: 3325 | T88: 3625 | U88: 3725 | V88: 4050 | W88: 4150 | X88: 29 | Y88: 80 | Z88: 200
E89: 900 | F89: 1700 | G89: 2350 | H89: 2550 | I89: 2800 | J89: 1275 | K89: 1325 | L89: 1275 | M89: 1325 | N89: 2025 | O89: 2125 | P89: 2025 | Q89: 2125 | R89: 2425 | S89: 2525 | T89: 2825 | U89: 2925 | V89: 3250 | W89: 3350 | X89: 29 | Y89: 20 | Z89: 120
C90: HAM / RTM / ANR | D90: Port Klang | E90: 900 | F90: 1650 | G90: 2350 | H90: 2550 | I90: 2850 | J90: 1275 | K90: 1425 | L90: 1275 | M90: 1425 | N90: 2125 | O90: 2225 | P90: 2125 | Q90: 2225 | R90: 2575 | S90: 2675 | T90: 2975 | U90: 3075 | V90: 3350 | W90: 3450 | X90: 29 | Y90: 80 | Z90: 200
B91: Bangkok (PAT) | C91: ZEE / WVN / HAM / RTM / ANR | D91: Singapore | E91: 900 | F91: 1700 | G91: 2200 | H91: 2450 | I91: 2700 | J91: 1275 | K91: 1375 | L91: 1275 | M91: 1375 | N91: 2025 | O91: 2125 | P91: 2025 | Q91: 2125 | R91: 2425 | S91: 2525 | T91: 2775 | U91: 2875 | V91: 3450 | W91: 3550 | X91: 26 | Y91: 20 | Z91: 120
E92: 900 | F92: 2500 | G92: 3050 | H92: 3250 | I92: 3500 | J92: 1275 | K92: 1375 | L92: 1275 | M92: 1375 | N92: 2825 | O92: 2925 | P92: 2825 | Q92: 2925 | R92: 3175 | S92: 3275 | T92: 3575 | U92: 3675 | V92: 3200 | W92: 3300 | X92: 26 | Y92: 80 | Z92: 200
B93: Bangkok (Sahatai) | C93: HAM / RTM / ANR | D93: Port Klang | E93: 900 | F93: 1650 | G93: 2200 | H93: 2450 | I93: 2750 | J93: 1275 | K93: 1375 | L93: 1275 | M93: 1375 | N93: 2125 | O93: 2225 | P93: 2125 | Q93: 2225 | R93: 2525 | S93: 2625 | T93: 2925 | U93: 3025 | V93: 4000 | W93: 4100 | X93: 26 | Y93: 80 | Z93: 200
B94: Ho Chi Minh | C94: ZEE / WVN / HAM / RTM / ANR | D94: Singapore | E94: 800 | F94: 2450 | G94: 3050 | H94: 3300 | I94: 3550 | J94: 1225 | K94: 1325 | L94: 1225 | M94: 1325 | N94: 2875 | O94: 2975 | P94: 2875 | Q94: 2975 | R94: 3125 | S94: 3225 | T94: 3575 | U94: 3675 | V94: 4000 | W94: 4100 | X94: 29
E95: 800 | F95: 1650 | G95: 2250 | H95: 2500 | I95: 2750 | J95: 1225 | K95: 1325 | L95: 1225 | M95: 1325 | N95: 2075 | O95: 2175 | P95: 2075 | Q95: 2175 | R95: 2325 | S95: 2425 | T95: 2775 | U95: 2875 | V95: 3200 | W95: 3300 | X95: 29 | Y95: 15 | Z95: 120
B96: Hai Phong | C96: ZEE / WVN / HAM / RTM / ANR | D96: Singapore | E96: 800 | F96: 2550 | G96: 3200 | H96: 3550 | I96: 3950 | J96: 1225 | K96: 1325 | L96: 1225 | M96: 1325 | N96: 3025 | O96: 3125 | P96: 3025 | Q96: 3125 | R96: 3425 | S96: 3525 | T96: 4075 | U96: 4175 | V96: 4850 | W96: 4950 | X96: 29 | Y96: 80 | Z96: 200
E97: 800 | F97: 1750 | G97: 2400 | H97: 2750 | I97: 3150 | J97: 1225 | K97: 1325 | L97: 1225 | M97: 1325 | N97: 2225 | O97: 2325 | P97: 2225 | Q97: 2325 | R97: 2625 | S97: 2725 | T97: 3275 | U97: 3375 | V97: 4050 | W97: 4150 | X97: 29 | Y97: 20 | Z97: 120
C98: HAM / RTM / ANR | D98: Port Klang | E98: 800 | F98: 1550 | G98: 3100 | H98: 3400 | I98: 3650 | J98: 1225 | K98: 1325 | L98: 1225 | M98: 1325 | N98: 1925 | O98: 2025 | P98: 1925 | Q98: 2025 | R98: 2225 | S98: 2325 | T98: 2725 | U98: 2825 | V98: 3150 | W98: 3250 | X98: 29 | Y98: 80 | Z98: 175
B99: Songkhla | C99: ZEE / WVN / HAM / RTM / ANR | D99: Singapore | E99: 1000 | F99: n.a. | G99: n.a. | H99: n.a. | I99: n.a. | J99: 1675 | K99: 1775 | L99: 1675 | M99: 1775 | N99: n.a. | O99: n.a. | P99: n.a. | Q99: n.a. | R99: n.a. | S99: n.a. | T99: n.a. | U99: n.a. | V99: n.a. | W99: n.a. | X99: 29
B101: China Wing Ports | C101: GATE IN + AMS / DOC fee where applicable + destination charges
B102: Anqing (Shenan) | C102: WVN / HAM / RTM / ANR / ZEE | D102: Shanghai | E102: 950 | F102: 2250 | G102: 2900 | H102: 3250 | I102: 3450 | J102: 1275 | K102: 1375 | L102: 1275 | M102: 1375 | N102: 2775 | O102: 2875 | P102: 2775 | Q102: 2875 | R102: 3075 | S102: 3175 | T102: 3675 | U102: 3775 | V102: 4000 | W102: 4100 | X102: 29 | Y102: 80 | Z102: 200
B103: Foshan (Lanshi) | C103: HAM / RTM / ANR / ZEE / WVN | D103: Yantian | E103: 875 | F103: 1400 | G103: 2100 | H103: 2450 | I103: 2700 | J103: 1025 | K103: 1125 | L103: 1025 | M103: 1125 | N103: 1775 | O103: 1875 | P103: 1775 | Q103: 1875 | R103: 2225 | S103: 2325 | T103: 2975 | U103: 3075 | V103: 3400 | W103: 3500 | X103: 24 | Y103: 80 | Z103: 200
B104: Huangpu New Port | C104: HAM / RTM / ANR / ZEE / WVN | D104: Yantian | E104: 750 | F104: 1300 | G104: 1900 | H104: 2150 | I104: 2400 | J104: 875 | K104: 975 | L104: 875 | M104: 975 | N104: 1525 | O104: 1625 | P104: 1525 | Q104: 1625 | R104: 1925 | S104: 2025 | T104: 2475 | U104: 2575 | V104: 2900 | W104: 3000 | X104: 29 | Y104: 80 | Z104: 200
B105: Jiangyin | C105: WVN / HAM / RTM / ANR / ZEE | D105: Shanghai | E105: 1000 | F105: 1450 | G105: 2150 | H105: 2400 | I105: 2600 | J105: 1275 | K105: 1375 | L105: 1275 | M105: 1375 | N105: 1875 | O105: 1975 | P105: 1875 | Q105: 1975 | R105: 2375 | S105: 2475 | T105: 2825 | U105: 2925 | V105: 3150 | W105: 3250 | X105: 24 | Y105: 80 | Z105: 100
B106: Jiangmen | C106: HAM / RTM / ANR / ZEE / WVN | D106: Yantian | E106: 800 | F106: 1350 | G106: 2000 | H106: 2300 | I106: 2550 | J106: 925 | K106: 1025 | L106: 925 | M106: 1025 | N106: 1675 | O106: 1775 | P106: 1675 | Q106: 1775 | R106: 2125 | S106: 2225 | T106: 2775 | U106: 2875 | V106: 3200 | W106: 3300 | X106: 24 | Y106: 80 | Z106: 100
B107: Ma'anshan | C107: WVN / HAM / RTM / ANR / ZEE | D107: Shanghai | E107: 1000 | F107: 1450 | G107: 2200 | H107: 2450 | I107: 2650 | J107: 1325 | K107: 1425 | L107: 1325 | M107: 1425 | N107: 1925 | O107: 2025 | P107: 1925 | Q107: 2025 | R107: 2425 | S107: 2525 | T107: 2875 | U107: 2975 | V107: 3200 | W107: 3300 | X107: 30 | Y107: 80 | Z107: 100
B108: Nanjing | C108: WVN / HAM / RTM / ANR / ZEE | D108: Shanghai | E108: 950 | F108: 2100 | G108: 2800 | H108: 3050 | I108: 3250 | J108: 1225 | K108: 1325 | L108: 1225 | M108: 1325 | N108: 2525 | O108: 2625 | P108: 2525 | Q108: 2625 | R108: 2975 | S108: 3075 | T108: 3425 | U108: 3525 | V108: 3750 | W108: 3850 | X108: 29 | Y108: 80 | Z108: 200
B109: Nansha | C109: HAM / RTM / ANR | D109: Port Klang | E109: 800 | F109: 1500 | G109: 2250 | H109: 2800 | I109: 3050 | J109: 925 | K109: 1025 | L109: 925 | M109: 1025 | N109: 1875 | O109: 1975 | P109: 1875 | Q109: 1975 | R109: 2575 | S109: 2675 | T109: 3425 | U109: 3525 | V109: 3850 | W109: 3850 | X109: 34**
B110: Nantong | C110: WVN / HAM / RTM / ANR / ZEE | D110: Shanghai | E110: 900 | F110: 2000 | G110: 2800 | H110: 3050 | I110: 3250 | J110: 1175 | K110: 1275 | L110: 1175 | M110: 1275 | N110: 2525 | O110: 2625 | P110: 2525 | Q110: 2625 | R110: 2925 | S110: 3025 | T110: 3375 | U110: 3475 | V110: 3700 | W110: 3800 | X110: 29 | Y110: 80 | Z110: 200
B111: Taicang | C111: WVN / HAM / RTM / ANR / ZEE | D111: Shanghai | E111: 950 | F111: 1350 | G111: 2000 | H111: 2300 | I111: 2500 | J111: 1175 | K111: 1275 | L111: 1175 | M111: 1275 | N111: 1675 | O111: 1775 | P111: 1675 | Q111: 1775 | R111: 1875 | S111: 1975 | T111: 2425 | U111: 2525 | V111: 2750 | W111: 2850 | X111: 34 | Y111: 80 | Z111: 160
B112: Wuhan | C112: WVN / HAM / RTM / ANR / ZEE | D112: Shanghai | E112: 1050 | F112: 1500 | G112: 2250 | H112: 2600 | I112: 2800 | J112: 1525 | K112: 1625 | L112: 1525 | M112: 1625 | N112: 2125 | O112: 2225 | P112: 2125 | Q112: 2225 | R112: 2625 | S112: 2725 | T112: 3275 | U112: 3375 | V112: 3600 | W112: 3700 | X112: 24.5 | Y112: 80 | Z112: 150
B113: Wuhu (Zhujiaqiao) | C113: WVN / HAM / RTM / ANR / ZEE | D113: Shanghai | E113: 950 | F113: 1400 | G113: 2150 | H113: 2400 | I113: 2600 | J113: 1225 | K113: 1325 | L113: 1225 | M113: 1325 | N113: 1875 | O113: 1975 | P113: 1875 | Q113: 1975 | R113: 2375 | S113: 2475 | T113: 2825 | U113: 2925 | V113: 3150 | W113: 3250 | X113: 24.5 | Y113: 80 | Z113: 150
B114: Yangzhou | C114: WVN / HAM / RTM / ANR / ZEE | D114: Shanghai | E114: 900 | F114: 2100 | G114: 2800 | H114: 3050 | I114: 3250 | J114: 1225 | K114: 1325 | L114: 1225 | M114: 1325 | N114: 2525 | O114: 2625 | P114: 2525 | Q114: 2625 | R114: 2975 | S114: 3075 | T114: 3425 | U114: 3525 | V114: 3750 | W114: 3850 | X114: 29 | Y114: 80 | Z114: 200
B115: Zhangjiagang | C115: WVN / HAM / RTM / ANR / ZEE | D115: Shanghai | E115: 900 | F115: 2000 | G115: 2800 | H115: 3050 | I115: 3250 | J115: 1175 | K115: 1275 | L115: 1175 | M115: 1275 | N115: 2525 | O115: 2625 | P115: 2525 | Q115: 2625 | R115: 2925 | S115: 3025 | T115: 3375 | U115: 3475 | V115: 3700 | W115: 3800 | X115: 29 | Y115: 80 | Z115: 200
...

Sheet Reefer
C3: Orient Overseas Container Line Ltd.
C4: REEFER EQUIPMENT
C5: Service Contract Number: RFT21181
C6: valid as from 01.12. - 31.01.2026
C9: Reefer shipments are on freight prepaid basis only
C10: Direct service only and subject to service change
C11: Only valid for foodstuffs and harmless low value cargo up to cargo value USD 499,999 per unit; Please check commodity acceptance with your local OOCL Sales; no hides & skins, high value cargo, pharmaceuticals and chemicals acceptable without carrier’s consent
C13: Please note that there may be restrictions regarding shipments of frozen meats to/via certain PODs, especially to Vietnam, Philippines and Malaysia; a pre-check of commodity and consignee details may be required before a shipment can be confirmed. Please check with your sales and customer service representative
C16: Far East/Middle East Eastbound : gate in subject to surcharges as per below, subject to destination surcharges
E17: POL ROTTERDAM | G17: POL Antwerpen | I17: POL HAMBURG | K17: POL WILHELMSHAVEN
C18: POD | D18: Currency | E18: Rate 20RF | F18: Rate 40RQ | G18: Rate 20RF | H18: Rate 40RQ | I18: Rate 20RF | J18: Rate 40RQ | K18: Rate 20RF | L18: Rate 40RQ
C19: Abu Dhabi, Abu Zabi, United Arab Emirates (direct only) | D19: USD | E19: 1244 | F19: 1700 | G19: 1244 | H19: 1700 | I19: 1344 | J19: 1800 | K19: No Offering | L19: No Offering
C20: Abu Dhabi, Abu Zabi, United Arab Emirates (via T/S Jebel Ali) | D20: USD | E20: 1544 | F20: 2000 | G20: 1544 | H20: 2000 | I20: 1644 | J20: 2100 | K20: No Offering | L20: No Offering
C21: Al Hidd, Muharraq Governorate, Bahrain | D21: USD | E21: 3200 | F21: 3100 | G21: 3200 | H21: 3100 | I21: 3200 | J21: 3100 | K21: No Offering | L21: No Offering
C22: Al Shuwaikh, Al Asamah, Kuwait | D22: USD | E22: 3200 | F22: 3100 | G22: 3200 | H22: 3100 | I22: 3200 | J22: 3100 | K22: No Offering | L22: No Offering
C23: Bangkok, Thailand | D23: USD | E23: 1400 | F23: 1300 | G23: 1500 | H23: 1400 | I23: 1600 | J23: 1500 | K23: 1600 | L23: 1500
C24: Busan, South Korea | D24: USD | E24: 1300 | F24: 1200 | G24: 1400 | H24: 1300 | I24: 1500 | J24: 1400 | K24: 1500 | L24: 1400
C25: Chongqing, China | D25: USD | E25: 2200 | F25: 2100 | G25: 2300 | H25: 2200 | I25: 2400 | J25: 2300 | K25: No Offering | L25: No Offering
C26: Colombo, Western, Sri Lanka | D26: USD | E26: 1720 | F26: 1620 | G26: 1820 | H26: 1720 | I26: 1920 | J26: 1820 | K26: No Offering | L26: No Offering
C27: Da Nang, Vietnam | D27: USD | E27: 3300 | F27: 3200 | G27: 3400 | H27: 3300 | I27: 3400 | J27: 3300 | K27: 3400 | L27: 3300
C28: Dalian, Dalian, Liaoning, China | D28: USD | E28: 1000 | F28: 900 | G28: 1100 | H28: 1000 | I28: 1200 | J28: 1100 | K28: No Offering | L28: No Offering
C29: Dammam, Ash Sharqiyah, Saudi Arabia | D29: USD | E29: 3200 | F29: 3100 | G29: 3200 | H29: 3100 | I29: 3200 | J29: 3100 | K29: No Offering | L29: No Offering
C30: Guangzhou, Guangzhou, Guangdong, China | D30: USD | E30: 1300 | F30: 1200 | G30: 1400 | H30: 1300 | I30: 1500 | J30: 1400 | K30: 1500 | L30: 1400
C31: Hai Phong, Vietnam | D31: USD | E31: 1500 | F31: 1400 | G31: 1600 | H31: 1500 | I31: 1700 | J31: 1600 | K31: 1700 | L31: 1600
C32: Hakata, Fukuoka, Japan | D32: USD | E32: 1600 | F32: 1500 | G32: 1700 | H32: 1600 | I32: 1800 | J32: 1700 | K32: 1800 | L32: 1700
C33: Ho Chi Minh, Vietnam | D33: USD | E33: 1690 | F33: 1590 | G33: 1790 | H33: 1690 | I33: 1890 | J33: 1790 | K33: 1890 | L33: 1790
C34: Hong Kong, Hong Kong, China | D34: USD | E34: 1500 | F34: 1400 | G34: 1600 | H34: 1500 | I34: 1700 | J34: 1600 | K34: No Offering | L34: No Offering
C35: Hong Kong, Hong Kong, China on LL3 only | D35: USD | E35: 1100 | F35: 1000 | G35: No Offering | H35: No Offering | I35: 1300 | J35: 1200 | K35: No Offering | L35: No Offering
C36: Huangpu, Guangzhou, Guangdong, China | D36: USD | E36: 1300 | F36: 1200 | G36: 1400 | H36: 1300 | I36: 1500 | J36: 1400 | K36: 1500 | L36: 1400
C37: Jakarta, Indonesia | D37: USD | E37: 1500 | F37: 1400 | G37: 1600 | H37: 1500 | I37: 1700 | J37: 1600 | K37: 1700 | L37: 1600
C38: Jebel Ali, Dubai, United Arab Emirates | D38: USD | E38: 2200 | F38: 2100 | G38: 2200 | H38: 2100 | I38: 2200 | J38: 2100 | K38: No Offering | L38: No Offering
C39: Jeddah, Makkah, Saudi Arabia | D39: currently no service
C40: Jiangmen, Jiangmen, Guangdong, China | D40: USD | E40: 1600 | F40: 1500 | G40: 1700 | H40: 1600 | I40: 1800 | J40: 1700 | K40: No Offering | L40: No Offering
C41: Kaohsiung, Taiwan | D41: USD | E41: 1000 | F41: 900 | G41: 1100 | H41: 1000 | I41: 1200 | J41: 1100 | K41: No Offering | L41: No Offering
C42: Keamari, Karachi, Sindh, Pakistan | D42: currently no service
C43: Keelung, Taiwan | D43: USD | E43: 1400 | F43: 1300 | G43: 1500 | H43: 1400 | I43: 1600 | J43: 1500 | K43: No Offering | L43: No Offering
C44: Kobe, Hyogo-ken, Japan | D44: USD | E44: 1400 | F44: 1300 | G44: 1500 | H44: 1400 | I44: 1600 | J44: 1500 | K44: 1600 | L44: 1500
C45: Laem Chabang, Chon Buri, Thailand | D45: USD | E45: 1500 | F45: 1400 | G45: 1600 | H45: 1500 | I45: 1700 | J45: 1600 | K45: 1700 | L45: 1600
C46: Lat Krabang, Bangkok, Thailand | D46: USD | E46: 1600 | F46: 1500 | G46: 1700 | H46: 1600 | I46: 1800 | J46: 1700 | K46: 1800 | L46: 1700
C47: Lianyungang, Lianyungang, Jiangsu, China | D47: USD | E47: 1600 | F47: 1500 | G47: 1700 | H47: 1600 | I47: 1800 | J47: 1700 | K47: 1800 | L47: 1700
C48: Macao, Macau, China | D48: USD | E48: 2200 | F48: 2100 | G48: 2300 | H48: 2200 | I48: 2400 | J48: 2300 | K48: No Offering | L48: No Offering
C49: Manila, Metro Manila, Philippines | D49: USD | E49: 2000 | F49: 1900 | G49: 2100 | H49: 2000 | I49: 2200 | J49: 2100 | K49: No Offering | L49: No Offering
C50: Nagoya, Aichi, Japan | D50: USD | E50: 1400 | F50: 1300 | G50: 1500 | H50: 1400 | I50: 1600 | J50: 1500 | K50: 1600 | L50: 1500
C51: Nansha, Guangzhou, Guangdong, China | D51: USD | E51: 1300 | F51: 1200 | G51: 1400 | H51: 1300 | I51: 1500 | J51: 1400 | K51: 1500 | L51: 1400
C52: Ningbo, Ningbo, Zhejiang, China | D52: USD | E52: 1000 | F52: 900 | G52: 1100 | H52: 1000 | I52: 1200 | J52: 1100 | K52: 1200 | L52: 1100
C53: Osaka, Japan | D53: USD | E53: 1400 | F53: 1300 | G53: 1500 | H53: 1400 | I53: 1600 | J53: 1500 | K53: 1600 | L53: 1500
C54: Pasir Gudang, Johor, Malaysia | D54: USD | E54: 1600 | F54: 1500 | G54: 1700 | H54: 1600 | I54: 1800 | J54: 1700 | K54: 1800 | L54: 1700
C55: Penang, Pulau Pinang, Malaysia | D55: USD | E55: 1600 | F55: 1500 | G55: 1700 | H55: 1600 | I55: 1800 | J55: 1700 | K55: 1800 | L55: 1700
C56: Port Klang, Selangor, Malaysia | D56: USD | E56: 1000 | F56: 900 | G56: 1100 | H56: 1000 | I56: 1200 | J56: 1100 | K56: No Offering | L56: No Offering
C57: Qingdao, Qingdao, Shandong, China | D57: USD | E57: 1000 | F57: 900 | G57: 1100 | H57: 1000 | I57: 1200 | J57: 1100 | K57: 1200 | L57: 1100
C58: Semarang, Jawa Tengah, Indonesia | D58: USD | E58: 1500 | F58: 1400 | G58: 1600 | H58: 1500 | I58: 1700 | J58: 1600 | K58: No Offering | L58: No Offering
C59: Shanghai, China | D59: USD | E59: 1000 | F59: 900 | G59: 1100 | H59: 1000 | I59: 1200 | J59: 1100 | K59: 1200 | L59: 1100
C60: Sharjah, United Arab Emirates | D60: USD | E60: 2970 | F60: 2870 | G60: 3070 | H60: 2970 | I60: 3170 | J60: 3070 | K60: No Offering | L60: No Offering
C61: Shekou, Shenzhen, Guangdong, China | D61: USD | E61: 1300 | F61: 1200 | G61: 1400 | H61: 1300 | I61: 1500 | J61: 1400 | K61: 1500 | L61: 1400
C62: Shimizu, Shizuoka, Japan | D62: USD | E62: 1900 | F62: 1800 | G62: 2000 | H62: 1900 | I62: 2100 | J62: 2000 | K62: 2100 | L62: 2000
C63: Singapore, Singapore | D63: USD | E63: 1300 | F63: 1200 | G63: 1400 | H63: 1300 | I63: 1500 | J63: 1400 | K63: 1200 | L63: 1100
C64: Surabaya, Jawa Timur, Indonesia | D64: USD | E64: 1500 | F64: 1400 | G64: 1600 | H64: 1500 | I64: 1700 | J64: 1600 | K64: 1700 | L64: 1600
C65: Taichung, Taiwan | D65: USD | E65: 1400 | F65: 1300 | G65: 1500 | H65: 1400 | I65: 1600 | J65: 1500 | K65: No Offering | L65: No Offering
C66: Taipei, Taiwan | D66: USD | E66: 1000 | F66: 900 | G66: 1100 | H66: 1000 | I66: 1200 | J66: 1100 | K66: No Offering | L66: No Offering
C67: Tan Thanh, Vung Tau, Ba Ria Vung Tau, Vietnam on LL3 only | D67: USD | E67: 1000 | F67: 900 | G67: No Offering | H67: No Offering | I67: 1200 | J67: 1100 | K67: No Offering | L67: No Offering
C68: Tokyo, Japan | D68: USD | E68: 1400 | F68: 1300 | G68: 1500 | H68: 1400 | I68: 1600 | J68: 1500 | K68: 1600 | L68: 1500
C69: Xiamen, Xiamen, Fujian, China on LL3/LL1 | D69: USD | E69: 1000 | F69: 900 | G69: No Offering | H69: No Offering | I69: 1200 | J69: 1100 | K69: 1200 | L69: 1100
C70: Xingang, Tianjin, China | D70: USD | E70: 1000 | F70: 900 | G70: 1100 | H70: 1000 | I70: 1200 | J70: 1100 | K70: No Offering | L70: No Offering
C71: Yantian, Shenzhen, Guangdong, China | D71: USD | E71: 1000 | F71: 900 | G71: 1100 | H71: 1000 | I71: 1200 | J71: 1100 | K71: 1200 | L71: 1100
C72: Zhangjiagang, Suzhou, Jiangsu, China | D72: USD | E72: 1500 | F72: 1400 | G72: 1600 | H72: 1500 | I72: 1700 | J72: 1600 | K72: 1700 | L72: 1600
C74: Australia | D74: GATE IN ALL IN ; subj. to AMS /DOC + destination charges
C75: POL Hamburg/Wilhelmshaven/Rotterdam/Antwerpen to POD | D75: Currency | E75: Rate 20RF | F75: Rate 40RQ
C76: Adelaide, South Australia, Australia | D76: USD | E76: 2300 | F76: 3200
C77: Auckland, Auckland, New Zealand | D77: USD | E77: 2300 | F77: 3200
C78: Brisbane, Queensland, Australia | D78: USD | E78: 2300 | F78: 3200
C79: Fremantle, Western Australia, Australia | D79: USD | E79: 2300 | F79: 3200
C80: Lyttelton, Canterbury, New Zealand | D80: USD | E80: 2300 | F80: 3200
C81: Melbourne, Victoria, Australia | D81: USD | E81: 2300 | F81: 3200
C82: Napier, Hawkes Bay, New Zealand | D82: USD | E82: 2300 | F82: 3200
C83: Sydney, New South Wales, Australia | D83: USD | E83: 2300 | F83: 3200
C84: Tauranga, Bay of Plenty, New Zealand | D84: USD | E84: 2300 | F84: 3200
C85: Wellington, Wellington, New Zealand | D85: USD | E85: 2300 | F85: 3200
C87: Intra Europe | D87: GATE IN ALL IN ; subj to AMS/DOC + destination charges
C88: Base Ports to Destination Port | D88: Routing | E88: 20RF | F88: 40RQ
C89: Piraeus | D89: direct | E89: - | F89: EUR 1600
C90: Ashdod | D90: via Piraeus | E90: USD 2100 | F90: USD 3000
C91: Haifa | D91: via Piraeus | E91: USD 1700 | F91: USD 3000
C92: Aliaga | D92: direct | E92: - | F92: EUR 1550
C93: Gebze | D93: direct | E93: - | F93: EUR 1550
C94: Istanbul | D94: direct | E94: - | F94: EUR 1550
C95: Mersin | D95: direct | E95: - | F95: EUR 1550
C96: Gemlik | D96: direct | E96: - | F96: EUR 1550
C97: El Dekheila* | D97: direct | E97: - | F97: EUR 1050
C98: * incl. 21 days dem/det in Egypt, subject to storage
C101: Far East/ Middle East/ Inida: RATE DATE IS SAILING DATE
C102: Australia/ New Zealand: RATE DATE IS ON BOARD DATE
C103: Intra Europe: RATE DATE IS GATE IN DATE
C105: included charges: BAF;CAF;GAS;SUZ;THC;IFP;FCR;EMS;ETS ; destination surcharges are applicable as per tariff on www.oocl.com (collect)
C106: -------------------------------------------
C107: plus following surcharges, valid until further notice
C108: EMS Far East, India, Middle East, Australia & NZL | D108: INCLUDED
C109: FCR Far East, India & Middle East (fuel cost recovery): | D109: INCLUDED
C110: FCR Australia & NZL (fuel cost recovery): | D110: INCLUDED
C111: FCR Intra Europe (fuel cost recovery): | D111: INCLUDED
C112: ETS Far East, India & Middle East: | D112: INCLUDED
...

Sheet pick up+Inland Tariff 
C5: Inland Tariff >> CLICK ME! | I5: Fahrplan / Schedule >> CLICK ME!
C7: demurrage - detention - restrictions >> CLICK ME! | I7: ODEZ_Inland_Terms_and_Conditions. >> CLICK ME!
C9: OOCL - Pick Up and Drop Off charges German hinterland >> CLICK ME!

Sheet Surcharges-Terms
D6: Origin charges (all listed on www.oocl.com/eng/resourcecenter/globalinfo/Pages/default.aspx )
D7: Destination charges (all listed on www.oocl.com/eng/resourcecenter/globalinfo/Pages/default.aspx )
C9: * For shipments to Fareast wingports & Australia / New Zealand (via Singapore) the following
C10: PSA additionals apply on top of a.m. DG-surcharge
C13: For your PSA Group please check with local OOCL Customer Service
C16: no acceptance for PSA 1 + PSA 2 not recommended via SIN t/s
C17: 1S, 2S, 2A, 2B, 2F, 3 | D17: DG is recommended for storage.
C18: 1D, 2 | D18: DG is not recommended for storage.
C19: ----------------------------------------
C20: PSA 3/2F/2S: SGD 180/360/405
C21: PSA 2B/2C: SGD 930/1485/1643
C22: PSA 2A: SGD 1080/1635/1793
C23: PSA 1S: SGD 380/560/605
C24: PSA 1C/1N: SGD 1130/1685/1843
C25: PSA 1/1D: SGD 1490/2405/2653
C26: PSA 2 (UN1057 only): SGD 1690/2605/2853
C27: PSA 2 (except UN1057): SGD 1290/2205/2453
C29: >>> ALL SUBJECT TO FINAL CARRIER ACCEPTANCE - CLASSES 1 & 7 ARE REJECTED
C31: Please use this link to check the acceptance of dangerous goods for transshipment in Port Kelang:
C32: http://pkapp.pka.gov.my/dg/unno.php?unno=3462&Search=Search
F35: China 24h rules
F36: Valid for ALL China + Japan Shipments !!
C38: DOCUMENTATION FEE | F38: Euro 75 | G38: pro B/L | H38: (applies for non-Electronic Shipping Instruction only (Documentation -> Shipping Instructions) via My OOCL.com)
C39: ADVANCED MANIFEST FEE (AMS) | F39: Euro 25 | G39: pro B/L | H39: shipments to/via China/Japan/Turkey/Egypt
C40: Amendments in addition (AAM) | F40: Euro 30 | G40: pro B/L | H40: shipments to/via China/Japan/Turkey/Egypt Customs system
C41: Cargo Manifest Amendment Fee (CMA) | F41: Euro 40 | G41: pro B/L | H41: corrections to shipments to/via China/Japan/Turkey/Egypt Carrier System
C42: Telex Release Fee | F42: Euro 60 | G42: pro B/L
C43: Late SI FEE | F43: Euro 80 | G43: pro B/L | H43: when providing BL instructions after SI cut off
C44: Manual booking fee | F44: Euro 40 | G44: per booking
C46: booking cancellation fees eff. 01.09.2023: | D46: http://www.oocl.com/germany/eng/localinformation/localsurcharges/Pages/default.aspx?site=germany&lang=eng
C48: General cargo dry - from 5 calendar days or less before gate in deadline EUR 100,- per container for cancelled or rolled bookings, including missing VGM/SI. (Except Destination Region Russia)
C49: Reefer/Dangerous goods/Special Equipment - from 5 calendar days or less before gate in deadline EUR 150,- per container for cancelled or rolled bookings, including missing VGM/SI (Except Destination)
C52: Certificates
C53: as Word Doc provided by customer | F53: Euro 25
C54: Data provided or certificate manually created by carrier | F54: Euro 50
C55: Notarized Certificate | F55: Euro 150
C59: HSS : | D59: In case Shipper fail to secure Cntr. with High Security Seal, then the Terminal Operator needs
D60: to re-seal the container without pre-notice. Terminal charges Euro 50 per Container / load location Euro 35 per Container, what OOCL has to
D61: charge to shipper without deduction - reduction.
C63: Customs RTM + ANR: | D63: All customs formalities (also for carriers haulage) to be arranged by shipper/forwarder themselves and must be completed at “CARGO CUT OFF DATE/TIME”
D64: as stated in the booking acknowledgement to ensure a smooth shipping.
D65: All details regarding safety & security must be listed in your export documents.
D66: The responsibility that all necessary documents have been received and accepted and processed by customs is in your hands.
D67: Carrier is not liable for any customs blockage (customs stop) as a result of customs matters.
D68: For further information please contact your customs broker.
C70: Port Shift Charge (SHF) | D70: Euro 75 per container for change of vessel / change of POD / delivery without or with wrong booking number
C72: Validity | D72: valid until date mentioned in front of the appropriate rate sheet
D73: rates are valid subject to space and equipment availability
D74: rates are valid to German based customers only
D75: local charges at origin and destination are not included in this offer and are subject to.
D76: Rates are not inclusive of all other surcharges, including those, if any,
D77: published in the Governing Tariff (s) at the time of shipment.
C80: Carrier' Haulage | D80: https://moc.oocl.com/wls_prs_rp/public/inlandTariff/search/display
C82: Payment terms
D83: Freight and charges are payable upon presentation of Bill of Lading. If customer wants
D84: a special agreement, OOCL will , after investigation, consider a special and mutual agreement
D85: with demanding party.
C88: Detention/Demurrage / Surcharge table / Restriction at discharging ports
D90: click here >>> | E90: http://www.oocl.com/eng/resourcecenter/globalinfo/
E92: and select the country of your interest
C95: Terms:
C96: Surcharges and fees are set at maximum, valid until further notice and are governed by prevailing tariffs published on www.oocl.com at time of shipment.
C97: All shipments are subject to vessel operators, planners and relevant third party approval.
C98: All offers are subject to space and equipment availability.
C99: We reserve the right to implement any surcharge at any time.
C100: Valid for under deck only, contact your local Sales to obtain appropriate pricing for on deck acceptance.
C101: We reserve the right to charge deadfreight in case of cancellations of lot shipments (consisting of 5 or more containers).
C102: For Special Equipment in Merchant’s Haulage the Carrier will not be liable for any damages to the tarpaulin for OT/OQ container during pre-carriages; any repair charges to be considered for the account of cargo.
C105: Important Notice: This Rate Document is subject to the Rate Document Terms and Conditions published on www.oocl.com, which has the payment and other terms and meaning of definitions used in the Rate Documents. Except for Surcharge and Fees marked as “Fixed” in this Rate Document, the quantum of other Surcharge and Fees in this Rate Document are set at maximum rates, valid until further notice (unless specified) and are governed by and subject to Carrier’s prevailing tariffs published on www.oocl.com at the time of shipment. Other Surcharge and Fees applicable include Surcharge and Fees introduced to cover a change of requirements or additional services at your request, contingency charges, local surcharges or other charges due to extraordinary conditions beyond OOCL’s control, if relevant, which are available at carrier’s prevailing governing tariff(s) on www.oocl.com at the time of shipment, and specified by OOCL* in its invoice(s) when your booking is accepted. Unless otherwise specified, all bookings are subject to carrier’s cargo acceptance, and availability of equipment, service loop and vessel space. All business transactions are undertaken in accordance with and subject to the carrier's Bills of Lading terms and conditions, which are available on www.oocl.com. OOCL* and carrier are defined in OOCL Bill of Lading. This Rate Document is governed by English Law.
C111: The parties agree to fully comply with General Data Protection Regulation 2016/679 (“GDPR”) and any applicable data protection laws and be bound by the terms available at http://www.oocl.com/eng/resourcecenter/industrylinks/Documents/Framework%20%28A%29-Shipper.pdf under which you are the “data controller” and OOCL is the “data processor” in respect of any personal data provided by you to us for the contract of carriage. You (i) authorise OOCL to process any personal data provided to OOCL or which is made available to OOCL by you for the purposes of providing service under the contract of carriage and the Rate Document and for other purposes including transferring personal data to competent bodies, courts or regulatory authorities, as may be requested; (ii) acknowledge and agree that OOCL may transfer the personal data to its affiliates, employees, agents, delegates, sub-processors or competent authorities and to a country outside of the European Economic Area in accordance with the “Model Clauses” at http://eur-lex.europa.eu/legal-content/EN/TXT/PDF/?uri=CELEX:32010D0087&from=en or “Ad hoc Clauses” at http://ec.europa.eu/justice/article-29/documentation/opinion-recommendation/files/2014/wp214_en.pdf and/or other available data transfer solutions.

Sheet Restricted Prohibited Commodity
A2: following commodites are either prohibited or need further checking:
A6: optional acceptance with conditions / further checking: | C6: prohibited commodities:
A7: Alcohol | C7: Charcoal + carbon related cargo
A8: Bone Meal | C8: Military Cargo
A9: Cacao Butter | C9: Waste / scrap
A10: Cargo in Flexitank | C10: Wet Hides
A11: Coils | C11: Whale, Dolphin and Shark and its related products
A12: Dangerous goods | C12: specie, bullion, precious or rare metals or stones, plate, jewellery or other objects of a rare or precious nature
A13: donation goods | C13: banknotes or other forms of currency
A14: Dry Hides / skins | C14: bonds or other negotiable instruments
A15: Fish Meal | C15: Lithium Batteries on LL4/LL5 service and for OOG if DG
A16: High and heavy density (= weight per single package (not loaded on pallet) is over 1000 kg)
A17: High value cargo
A18: Lithium Batteries (except LL4/LL5 service)
A19: Magnetic iron/materials
A20: NI-MH Batteries (Nickel-Metal-Hydrid Batteries)
A21: Personal effects (Canada-USA cross-boarder & Door-Deliveries prohibited)
A22: Rubber
A23: Silicon briquette
A24: Steel
A25: used cargo

Sheet OOG booking check list
B2: AWKWARD SHIPMENT – CHECKLISTE (effective 13.06.2019)
B5: Ø Each change of awkward details (for example: overdimension / weight) causes
B6: cancellation of existing „acceptances“.
B7: Following steps may help to smoothen the process of new application but are
B8: no guarantee for final loading.
B10: Ø Finally changed over-dimensions (as well as dimension and weight of single
B11: pieces) have to be advised to OOCL immediately, latest until VGM-cut off.
B13: Ø Booking, booked over-dimensions, cargo dimension and picked up container
B14: are linked and related to each other. Any mix up of containers must be
B15: advised to OOCL immediately, latest until VGM- cut off.
B17: Ø Type of stowage must be advised: overwidth centered / one side only.
B18: If oversize both sides is not centered i. e. due to “center of gravity” –
... B24: of loading). Any findings may result in non-shipment and/or costs.
